{"_id":{"$oid":"5937a479421aa949b219ea06"},"active":true,"authorizedServices":{},"id":"AMX_Ent_1119695","isEnterprise":"true","lastModified":{"$date":"2016-04-28T07:00:09.015Z"},"productType":"cloudpbx"}
{"_id":{"$oid":"5937a479421aa949b219ea20"},"active":false,"authorizedServices":{},"id":"AMX_Ent_1270990","isEnterprise":"true","lastModified":{"$date":"2017-09-21T07:00:04.116Z"},"productType":"cloudpbx"}
{"_id":{"$oid":"5937a47a421aa949b219ea8f"},"active":true,"authorizedServices":{},"id":"AMX_Ent_1318303","isEnterprise":"true","lastModified":{"$date":"2016-04-28T07:00:09.015Z"},"productType":"cloudpbx"}
{"_id":{"$oid":"5937a47a421aa949b219eaad"},"active":true,"authorizedServices":{},"id":"AMX_Ent_1322847","isEnterprise":"true","lastModified":{"$date":"2016-04-28T07:00:09.015Z"},"productType":"cloudpbx"}
{"_id":{"$oid":"5937a47a421aa949b219eac8"},"active":true,"authorizedServices":{},"id":"AMX_Ent_1333022","isEnterprise":"true","lastModified":{"$date":"2016-04-28T07:00:09.015Z"},"productType":"cloudpbx"}
{"_id":{"$oid":"5937a47a421aa949b219eaf1"},"active":true,"authorizedServices":{},"id":"AMX_Ent_1333158","isEnterprise":"true","lastModified":{"$date":"2016-04-28T07:00:09.015Z"},"productType":"cloudpbx"}
{"_id":{"$oid":"5937a47a421aa949b219eb59"},"active":true,"authorizedServices":{},"id":"AMX_Ent_1340057","isEnterprise":"true","lastModified":{"$date":"2016-04-28T07:00:09.015Z"},"productType":"cloudpbx"}
{"_id":{"$oid":"5937a47a421aa949b219eb72"},"active":true,"authorizedServices":{},"id":"AMX_Ent_1357549","isEnterprise":"true","lastModified":{"$date":"2016-04-28T07:00:09.015Z"},"productType":"cloudpbx"}
{"_id":{"$oid":"5937a47a421aa949b219eb8b"},"active":true,"authorizedServices":{},"id":"AMX_Ent_1381018","isEnterprise":"true","lastModified":{"$date":"2016-04-28T07:00:09.015Z"},"productType":"cloudpbx"}
{"_id":{"$oid":"5937a47a421aa949b219ebfd"},"active":false,"authorizedServices":{},"id":"AMX_Ent_1387371","isEnterprise":"true","lastModified":{"$date":"2016-10-05T08:24:34.593Z"},"productType":"cloudpbx"}
{"_id":{"$oid":"5937a47b421aa949b219ec36"},"active":true,"authorizedServices":{},"id":"AMX_Ent_1388110","isEnterprise":"true","lastModified":{"$date":"2016-04-28T07:00:09.015Z"},"productType":"cloudpbx"}
{"_id":{"$oid":"5937a47b421aa949b219ec53"},"active":true,"authorizedServices":{},"id":"AMX_Ent_1389358","isEnterprise":"true","lastModified":{"$date":"2016-04-28T07:00:09.015Z"},"productType":"cloudpbx"}
{"_id":{"$oid":"5937a47b421aa949b219ec9e"},"active":true,"authorizedServices":{},"id":"AMX_Ent_1391245","isEnterprise":"true","lastModified":{"$date":"2016-04-28T07:00:09.015Z"},"productType":"cloudpbx"}
{"_id":{"$oid":"5937a47b421aa949b219ecb5"},"active":true,"authorizedServices":{},"id":"AMX_Ent_1391317","isEnterprise":"true","lastModified":{"$date":"2016-04-28T07:00:09.015Z"},"productType":"cloudpbx"}
{"_id":{"$oid":"5937a47b421aa949b219ece4"},"active":true,"authorizedServices":{},"id":"AMX_Ent_1394508","isEnterprise":"true","lastModified":{"$date":"2016-04-28T07:00:09.015Z"},"productType":"cloudpbx"}
{"_id":{"$oid":"5937a47b421aa949b219ecef"},"active":true,"authorizedServices":{},"id":"AMX_Ent_1399592","isEnterprise":"true","lastModified":{"$date":"2016-04-28T07:00:09.015Z"},"productType":"cloudpbx"}
{"_id":{"$oid":"5937a47b421aa949b219ecff"},"active":true,"authorizedServices":{},"id":"AMX_Ent_1399988","isEnterprise":"true","lastModified":{"$date":"2016-04-28T07:00:09.015Z"},"productType":"cloudpbx"}
{"_id":{"$oid":"5937a47b421aa949b219ed2a"},"active":true,"authorizedServices":{},"id":"AMX_Ent_1400481","isEnterprise":"true","lastModified":{"$date":"2016-04-28T07:00:09.015Z"},"productType":"cloudpbx"}
{"_id":{"$oid":"5937a47b421aa949b219ed3d"},"active":true,"authorizedServices":{},"id":"AMX_Ent_1403308","isEnterprise":"true","lastModified":{"$date":"2016-04-28T07:00:09.015Z"},"productType":"cloudpbx"}
{"_id":{"$oid":"5937a47b421aa949b219ed48"},"active":true,"authorizedServices":{},"id":"AMX_Ent_1405603","isEnterprise":"true","lastModified":{"$date":"2016-04-28T07:00:09.015Z"},"productType":"cloudpbx"}
{"_id":{"$oid":"5937a47b421aa949b219ed53"},"active":true,"authorizedServices":{},"id":"AMX_Ent_1406174","isEnterprise":"true","lastModified":{"$date":"2016-04-28T07:00:09.015Z"},"productType":"cloudpbx"}
{"_id":{"$oid":"5937a47b421aa949b219ed5e"},"active":false,"authorizedServices":{},"id":"AMX_Ent_1406871","isEnterprise":"true","lastModified":{"$date":"2018-02-16T08:00:03.605Z"},"productType":"cloudpbx"}
{"_id":{"$oid":"5937a47b421aa949b219ed69"},"active":true,"authorizedServices":{},"id":"AMX_Ent_1406902","isEnterprise":"true","lastModified":{"$date":"2016-04-28T07:00:09.015Z"},"productType":"cloudpbx"}
{"_id":{"$oid":"5937a47b421aa949b219ed74"},"active":true,"authorizedServices":{},"id":"AMX_Ent_1407504","isEnterprise":"true","lastModified":{"$date":"2016-04-28T07:00:09.015Z"},"productType":"cloudpbx"}
{"_id":{"$oid":"5937a47b421aa949b219ed7f"},"active":true,"authorizedServices":{},"id":"AMX_Ent_1408598","isEnterprise":"true","lastModified":{"$date":"2016-04-28T07:00:09.015Z"},"productType":"cloudpbx"}
{"_id":{"$oid":"5937a47b421aa949b219ed8a"},"active":true,"authorizedServices":{},"id":"AMX_Ent_1408697","isEnterprise":"true","lastModified":{"$date":"2016-04-28T07:00:09.015Z"},"productType":"cloudpbx"}
{"_id":{"$oid":"5937a47b421aa949b219ed95"},"active":true,"authorizedServices":{},"id":"AMX_Ent_1408752","isEnterprise":"true","lastModified":{"$date":"2016-04-28T07:00:09.015Z"},"productType":"cloudpbx"}
{"_id":{"$oid":"5937a47b421aa949b219edd7"},"active":true,"authorizedServices":{},"id":"telmex","isEnterprise":"true","lastModified":{"$date":"2016-04-28T07:00:09.015Z"},"productType":"cloudpbx"}
{"_id":{"$oid":"5937a488421aa949b219f3a8"},"active":true,"authorizedServices":{},"id":"AMX_Ent_1410143","isEnterprise":"true","lastModified":{"$date":"2016-05-03T07:00:21.897Z"},"productType":"cloudpbx"}
{"_id":{"$oid":"5937a495421aa949b219f5ce"},"active":true,"authorizedServices":{},"id":"AMX_Ent_1410414","isEnterprise":"true","lastModified":{"$date":"2016-05-08T07:00:35.276Z"},"productType":"cloudpbx"}
{"_id":{"$oid":"5937a495421aa949b219f5dc"},"active":true,"authorizedServices":{},"id":"AMX_Ent_1410538","isEnterprise":"true","lastModified":{"$date":"2016-05-08T07:00:35.276Z"},"productType":"cloudpbx"}
{"_id":{"$oid":"5937a4a2421aa949b219fc10"},"active":false,"authorizedServices":{},"id":"AMX_Ent_1412353","isEnterprise":"true","lastModified":{"$date":"2016-05-22T07:01:07.723Z"},"productType":"cloudpbx"}
{"_id":{"$oid":"5937a4ae421aa949b21a0053"},"active":true,"authorizedServices":{},"id":"AMX_Ent_1413253","isEnterprise":"true","lastModified":{"$date":"2016-05-18T07:01:00.158Z"},"productType":"cloudpbx"}
{"_id":{"$oid":"5937a4ae421aa949b21a00a6"},"active":true,"authorizedServices":{},"id":"AMX_Ent_1413470","isEnterprise":"true","lastModified":{"$date":"2016-05-18T07:01:00.158Z"},"productType":"cloudpbx"}
{"_id":{"$oid":"5937a4be421aa949b21a053f"},"active":true,"authorizedServices":{},"id":"AMX_Ent_1415425","isEnterprise":"true","lastModified":{"$date":"2016-05-26T07:01:15.219Z"},"productType":"cloudpbx"}
{"_id":{"$oid":"5937a4be421aa949b21a054a"},"active":true,"authorizedServices":{},"id":"AMX_Ent_1416182","isEnterprise":"true","lastModified":{"$date":"2016-05-26T07:01:15.219Z"},"productType":"cloudpbx"}
{"_id":{"$oid":"5937a4be421aa949b21a0555"},"active":false,"authorizedServices":{},"id":"AMX_Ent_1416395","isEnterprise":"true","lastModified":{"$date":"2016-06-16T07:09:02.468Z"},"productType":"cloudpbx"}
{"_id":{"$oid":"5937a4be421aa949b21a0560"},"active":true,"authorizedServices":{},"id":"AMX_Ent_1416656","isEnterprise":"true","lastModified":{"$date":"2016-05-26T07:01:15.219Z"},"productType":"cloudpbx"}
{"_id":{"$oid":"5937a4c4421aa949b21a07a7"},"active":true,"authorizedServices":{},"id":"AMX_Ent_1417194","isEnterprise":"true","lastModified":{"$date":"2016-05-29T07:01:21.900Z"},"productType":"cloudpbx"}
{"_id":{"$oid":"5937a4cd421aa949b21a09f3"},"active":true,"authorizedServices":{},"id":"AMX_Ent_1417891","isEnterprise":"true","lastModified":{"$date":"2016-06-02T07:01:29.619Z"},"productType":"cloudpbx"}
{"_id":{"$oid":"5937a4cd421aa949b21a0a0d"},"active":false,"authorizedServices":{},"id":"AMX_Ent_1418386","isEnterprise":"true","lastModified":{"$date":"2017-08-14T07:00:03.489Z"},"productType":"cloudpbx"}
{"_id":{"$oid":"5937a4cd421aa949b21a0a3c"},"active":true,"authorizedServices":{},"id":"AMX_Ent_1419198","isEnterprise":"true","lastModified":{"$date":"2016-06-02T07:01:29.619Z"},"productType":"cloudpbx"}
{"_id":{"$oid":"5937a4d6421aa949b21a0b3e"},"active":true,"authorizedServices":{"attributes":[{"name":"maxTrunkGroupSimultaneousCalls","value":0}],"name":"TrunkGroup"},"id":"Automator","isEnterprise":"true","lastModified":{"$date":"2016-06-05T07:01:39.010Z"},"productType":"cuad"}
{"_id":{"$oid":"5937a4d6421aa949b21a0b94"},"active":false,"authorizedServices":{},"id":"BBVA","isEnterprise":"true","lastModified":{"$date":"2016-09-26T08:15:08.305Z"},"productType":"cuad"}
{"_id":{"$oid":"5937a4d7421aa949b21a0c83"},"active":true,"authorizedServices":{},"id":"Bufete_RM","isEnterprise":"true","lastModified":{"$date":"2016-06-05T07:01:39.010Z"},"productType":"cuad"}
{"_id":{"$oid":"5937a4d7421aa949b21a0d9e"},"active":true,"authorizedServices":{},"id":"CFE","isEnterprise":"true","lastModified":{"$date":"2016-06-05T07:01:39.010Z"},"productType":"cuad"}
{"_id":{"$oid":"5937a4d7421aa949b21a0da6"},"active":true,"authorizedServices":{},"id":"Devlyn","isEnterprise":"true","lastModified":{"$date":"2016-06-05T07:01:39.010Z"},"productType":"cuad"}
{"_id":{"$oid":"5937a4d8421aa949b21a0ea5"},"active":true,"authorizedServices":{},"id":"Diageo","isEnterprise":"true","lastModified":{"$date":"2016-06-05T07:01:39.010Z"},"productType":"cuad"}
{"_id":{"$oid":"5937a4d9421aa949b21a0f81"},"active":true,"authorizedServices":{},"id":"Euroelectrica","isEnterprise":"true","lastModified":{"$date":"2016-06-05T07:01:39.010Z"},"productType":"cuad"}
{"_id":{"$oid":"5937a4db421aa949b21a1198"},"active":true,"authorizedServices":{},"id":"Famosa","isEnterprise":"true","lastModified":{"$date":"2016-06-05T07:01:39.010Z"},"productType":"cuad"}
{"_id":{"$oid":"5937a4db421aa949b21a119e"},"active":false,"authorizedServices":{},"id":"First.Majestic","isEnterprise":"true","lastModified":{"$date":"2016-06-30T07:26:55.120Z"},"productType":"cuad"}
{"_id":{"$oid":"5937a4dc421aa949b21a1398"},"active":true,"authorizedServices":{"attributes":[{"name":"maxTrunkGroupSimultaneousCalls","value":0}],"name":"TrunkGroup"},"id":"GDF","isEnterprise":"true","lastModified":{"$date":"2016-06-05T07:01:39.010Z"},"productType":"cuad"}
{"_id":{"$oid":"5937a4dc421aa949b21a13f4"},"active":false,"authorizedServices":{},"id":"GEBOY","isEnterprise":"true","lastModified":{"$date":"2017-02-22T10:49:52.128Z"},"productType":"cuad"}
{"_id":{"$oid":"5937a4dc421aa949b21a1459"},"active":true,"authorizedServices":{},"id":"IESAC","isEnterprise":"true","lastModified":{"$date":"2016-06-05T07:01:39.010Z"},"productType":"cuad"}
{"_id":{"$oid":"5937a4dd421aa949b21a151f"},"active":true,"authorizedServices":{},"id":"IMSS","isEnterprise":"true","lastModified":{"$date":"2016-06-05T07:01:39.010Z"},"productType":"cuad"}
{"_id":{"$oid":"5937a4dd421aa949b21a1525"},"active":true,"authorizedServices":{},"id":"Massive Loads","isEnterprise":"true","lastModified":{"$date":"2016-06-05T07:01:39.010Z"},"productType":"cuad"}
{"_id":{"$oid":"5937a4e5421aa949b21a1f64"},"active":true,"authorizedServices":{},"id":"Modatelas","isEnterprise":"true","lastModified":{"$date":"2016-06-05T07:01:39.010Z"},"productType":"cuad"}
{"_id":{"$oid":"5937a4e5421aa949b21a1f68"},"active":true,"authorizedServices":{},"id":"Nomenclatura","isEnterprise":"true","lastModified":{"$date":"2016-06-05T07:01:39.010Z"},"productType":"cuad"}
{"_id":{"$oid":"5937a4e8421aa949b21a243b"},"active":true,"authorizedServices":{},"id":"Oriflame","isEnterprise":"true","lastModified":{"$date":"2016-06-05T07:01:39.010Z"},"productType":"cuad"}
{"_id":{"$oid":"5937a4e8421aa949b21a2441"},"active":true,"authorizedServices":{},"id":"PM.Expeditions","isEnterprise":"true","lastModified":{"$date":"2016-06-05T07:01:39.010Z"},"productType":"cuad"}
{"_id":{"$oid":"5937a539421aa949b21a79a9"},"active":true,"authorizedServices":{"attributes":[{"name":"maxTrunkGroupSimultaneousCalls","value":0}],"name":"TrunkGroup"},"id":"Telmex","isEnterprise":"true","lastModified":{"$date":"2016-06-05T07:01:39.010Z"},"productType":"cuad"}
{"_id":{"$oid":"5937a539421aa949b21a79c7"},"active":true,"authorizedServices":{},"id":"Troncal_IP","isEnterprise":"true","lastModified":{"$date":"2016-06-05T07:01:39.010Z"},"productType":"cuad"}
{"_id":{"$oid":"5937a539421aa949b21a79d3"},"active":true,"authorizedServices":{},"id":"Vector","isEnterprise":"true","lastModified":{"$date":"2016-06-05T07:01:39.010Z"},"productType":"cuad"}
{"_id":{"$oid":"5937a53a421aa949b21a7c03"},"active":false,"authorizedServices":{},"id":"VickyForm","isEnterprise":"true","lastModified":{"$date":"2017-04-26T14:36:04.048Z"},"productType":"cuad"}
{"_id":{"$oid":"5937a540421aa949b21a844e"},"active":true,"authorizedServices":{"attributes":[{"name":"maxTrunkGroupSimultaneousCalls","value":100}],"name":"TrunkGroup"},"id":"Vsys","isEnterprise":"true","lastModified":{"$date":"2016-06-05T07:01:39.010Z"},"productType":"cuad"}
{"_id":{"$oid":"5937a54c421aa949b21a8a94"},"active":true,"authorizedServices":{},"id":"fiscaliatabasco","isEnterprise":"true","lastModified":{"$date":"2016-06-05T07:01:39.010Z"},"productType":"cuad"}
{"_id":{"$oid":"5937a551421aa949b21a8e62"},"active":true,"authorizedServices":{},"id":"kidzania","isEnterprise":"true","lastModified":{"$date":"2016-06-05T07:01:39.010Z"},"productType":"cuad"}
{"_id":{"$oid":"5937a557421aa949b21a90a9"},"active":true,"authorizedServices":{},"id":"AMX_Ent_1420222","isEnterprise":"true","lastModified":{"$date":"2016-06-06T07:03:45.789Z"},"productType":"cloudpbx"}
{"_id":{"$oid":"5937a55b421aa949b21a9127"},"active":true,"authorizedServices":{},"id":"AMX_Ent_1221947","isEnterprise":"true","lastModified":{"$date":"2016-06-09T07:03:54.650Z"},"productType":"cloudpbx"}
{"_id":{"$oid":"5937a55f421aa949b21a9352"},"active":true,"authorizedServices":{},"id":"AMX_Ent_1420900","isEnterprise":"true","lastModified":{"$date":"2016-06-09T07:03:54.650Z"},"productType":"cloudpbx"}
{"_id":{"$oid":"5937a56f421aa949b21aaba4"},"active":true,"authorizedServices":{},"id":"AmericaMovil","isEnterprise":"true","lastModified":{"$date":"2016-06-09T07:04:00.275Z"},"productType":"uc"}
{"_id":{"$oid":"5937a56f421aa949b21aaba6"},"active":true,"authorizedServices":{},"id":"AudioBridge LATAM","isEnterprise":"true","lastModified":{"$date":"2016-06-09T07:04:00.275Z"},"productType":"uc"}
{"_id":{"$oid":"5937a570421aa949b21aabd8"},"active":true,"authorizedServices":{},"id":"AudioBridgeProvider","isEnterprise":"false","lastModified":{"$date":"2016-06-09T07:04:00.275Z"},"productType":"uc"}
{"_id":{"$oid":"5937a57d421aa949b21aafed"},"active":true,"authorizedServices":{},"id":"IEEG","isEnterprise":"true","lastModified":{"$date":"2016-06-09T07:04:17.725Z"},"productType":"cuad"}
{"_id":{"$oid":"5937a607421aa949b21afa30"},"active":true,"authorizedServices":{},"id":"CECOR","isEnterprise":"true","lastModified":{"$date":"2016-06-13T07:06:42.263Z"},"productType":"cuad"}
{"_id":{"$oid":"5937a68f421aa949b21b47ac"},"active":true,"authorizedServices":{},"id":"AMX_Ent_1247061","isEnterprise":"true","lastModified":{"$date":"2016-06-16T07:09:02.468Z"},"productType":"cloudpbx"}
{"_id":{"$oid":"5937a695421aa949b21b49ea"},"active":true,"authorizedServices":{},"id":"AMX_Ent_1421302","isEnterprise":"true","lastModified":{"$date":"2016-06-16T07:09:02.468Z"},"productType":"cloudpbx"}
{"_id":{"$oid":"5937a695421aa949b21b49fe"},"active":true,"authorizedServices":{},"id":"AMX_Ent_1421450","isEnterprise":"true","lastModified":{"$date":"2016-06-16T07:09:02.468Z"},"productType":"cloudpbx"}
{"_id":{"$oid":"5937a695421aa949b21b4a09"},"active":true,"authorizedServices":{},"id":"AMX_Ent_1421478","isEnterprise":"true","lastModified":{"$date":"2016-06-16T07:09:02.468Z"},"productType":"cloudpbx"}
{"_id":{"$oid":"5937a7af421aa949b21baa9c"},"active":true,"authorizedServices":{},"id":"Audioconferencias_Telmex","isEnterprise":"true","lastModified":{"$date":"2016-06-21T07:13:47.449Z"},"productType":"cuad"}
{"_id":{"$oid":"5937a8a0421aa949b21c4aae"},"active":false,"authorizedServices":{},"id":"vector1","isEnterprise":"true","lastModified":{"$date":"2016-08-22T08:05:03.501Z"},"productType":"cuad"}
{"_id":{"$oid":"5937a8a7421aa949b21c4b20"},"active":true,"authorizedServices":{},"id":"AMX_Ent_1263806","isEnterprise":"true","lastModified":{"$date":"2016-06-23T07:17:58.436Z"},"productType":"cloudpbx"}
{"_id":{"$oid":"5937ac1a421aa949b21dfd5d"},"active":true,"authorizedServices":{},"id":"AMX_Ent_1267401","isEnterprise":"true","lastModified":{"$date":"2016-07-07T07:32:39.959Z"},"productType":"cloudpbx"}
{"_id":{"$oid":"5937ae48421aa949b21ed8de"},"active":true,"authorizedServices":{},"id":"AMX_Ent_1430848","isEnterprise":"true","lastModified":{"$date":"2016-07-21T07:41:51.489Z"},"productType":"cloudpbx"}
{"_id":{"$oid":"5937ae48421aa949b21ed8e9"},"active":true,"authorizedServices":{},"id":"AMX_Ent_1430850","isEnterprise":"true","lastModified":{"$date":"2016-07-21T07:41:51.489Z"},"productType":"cloudpbx"}
{"_id":{"$oid":"5937ae48421aa949b21ed8f4"},"active":true,"authorizedServices":{},"id":"AMX_Ent_1431023","isEnterprise":"true","lastModified":{"$date":"2016-07-21T07:41:51.489Z"},"productType":"cloudpbx"}
{"_id":{"$oid":"5937ae48421aa949b21ed8ff"},"active":true,"authorizedServices":{},"id":"AMX_Ent_1431183","isEnterprise":"true","lastModified":{"$date":"2016-07-21T07:41:51.489Z"},"productType":"cloudpbx"}
{"_id":{"$oid":"5937af06421aa949b21ed941"},"active":true,"authorizedServices":{},"id":"AMX_Ent_1107645","isEnterprise":"true","lastModified":{"$date":"2016-07-28T07:45:09.791Z"},"productType":"cloudpbx"}
{"_id":{"$oid":"5937af0c421aa949b21edc5a"},"active":true,"authorizedServices":{},"id":"AMX_Ent_1431382","isEnterprise":"true","lastModified":{"$date":"2016-07-28T07:45:09.791Z"},"productType":"cloudpbx"}
{"_id":{"$oid":"5937af0c421aa949b21edc65"},"active":true,"authorizedServices":{},"id":"AMX_Ent_1431579","isEnterprise":"true","lastModified":{"$date":"2016-07-28T07:45:09.791Z"},"productType":"cloudpbx"}
{"_id":{"$oid":"5937af0d421aa949b21edc70"},"active":true,"authorizedServices":{},"id":"AMX_Ent_1431886","isEnterprise":"true","lastModified":{"$date":"2016-07-28T07:45:09.791Z"},"productType":"cloudpbx"}
{"_id":{"$oid":"5937af0d421aa949b21edc99"},"active":true,"authorizedServices":{},"id":"AMX_Ent_1431907","isEnterprise":"true","lastModified":{"$date":"2016-07-28T07:45:09.791Z"},"productType":"cloudpbx"}
{"_id":{"$oid":"5937af0d421aa949b21edca9"},"active":true,"authorizedServices":{},"id":"AMX_Ent_1432786","isEnterprise":"true","lastModified":{"$date":"2016-07-28T07:45:09.791Z"},"productType":"cloudpbx"}
{"_id":{"$oid":"5937af47421aa949b21ef11b"},"active":true,"authorizedServices":{},"id":"GCM","isEnterprise":"true","lastModified":{"$date":"2016-07-28T07:46:01.747Z"},"productType":"cuad"}
{"_id":{"$oid":"5937af55421aa949b21ef819"},"active":true,"authorizedServices":{},"id":"NSJPBCS","isEnterprise":"true","lastModified":{"$date":"2016-07-28T07:46:01.747Z"},"productType":"cuad"}
{"_id":{"$oid":"5937afce421aa949b21f427a"},"active":true,"authorizedServices":{},"id":"AMX_Ent_1433528","isEnterprise":"true","lastModified":{"$date":"2016-08-03T07:48:21.430Z"},"productType":"cloudpbx"}
{"_id":{"$oid":"5937afd6421aa949b21f42fd"},"active":true,"authorizedServices":{},"id":"AMX_Ent_1203553","isEnterprise":"true","lastModified":{"$date":"2016-08-04T07:48:37.083Z"},"productType":"cloudpbx"}
{"_id":{"$oid":"5937afdd421aa949b21f45e7"},"active":true,"authorizedServices":{},"id":"AMX_Ent_1434516","isEnterprise":"true","lastModified":{"$date":"2016-08-04T07:48:37.083Z"},"productType":"cloudpbx"}
{"_id":{"$oid":"5937afff421aa949b21f5a13"},"active":false,"authorizedServices":{},"id":"Farmacia_Regis","isEnterprise":"true","lastModified":{"$date":"2017-02-20T10:43:33.507Z"},"productType":"cuad"}
{"_id":{"$oid":"5937b0e3421aa949b21ffadd"},"active":true,"authorizedServices":{},"id":"AMX_Ent_1434910","isEnterprise":"true","lastModified":{"$date":"2016-08-10T07:52:58.329Z"},"productType":"cloudpbx"}
{"_id":{"$oid":"5937b166421aa949b2205139"},"active":false,"authorizedServices":{},"id":"AMX_Ent_1435817","isEnterprise":"true","lastModified":{"$date":"2018-03-07T08:00:03.838Z"},"productType":"cloudpbx"}
{"_id":{"$oid":"5937b24c421aa949b220f7fb"},"active":true,"authorizedServices":{},"id":"UNAM","isEnterprise":"true","lastModified":{"$date":"2016-08-14T07:57:38.567Z"},"productType":"cuad"}
{"_id":{"$oid":"5937b281421aa949b2210566"},"active":true,"authorizedServices":{},"id":"AMX_Ent_1397788","isEnterprise":"true","lastModified":{"$date":"2017-11-30T08:00:04.056Z"},"productType":"cloudpbx"}
{"_id":{"$oid":"5937b281421aa949b221057a"},"active":true,"authorizedServices":{},"id":"AMX_Ent_1398174","isEnterprise":"true","lastModified":{"$date":"2016-08-18T07:59:57.248Z"},"productType":"cloudpbx"}
{"_id":{"$oid":"5937b286421aa949b2210796"},"active":true,"authorizedServices":{},"id":"AMX_Ent_1435834","isEnterprise":"true","lastModified":{"$date":"2016-08-18T07:59:57.248Z"},"productType":"cloudpbx"}
{"_id":{"$oid":"5937b286421aa949b22107a1"},"active":false,"authorizedServices":{},"id":"AMX_Ent_1436234","isEnterprise":"true","lastModified":{"$date":"2017-08-29T07:00:03.233Z"},"productType":"cloudpbx"}
{"_id":{"$oid":"5937b286421aa949b22107be"},"active":true,"authorizedServices":{},"id":"AMX_Ent_1436250","isEnterprise":"true","lastModified":{"$date":"2016-08-18T07:59:57.248Z"},"productType":"cloudpbx"}
{"_id":{"$oid":"5937b286421aa949b22107c9"},"active":true,"authorizedServices":{},"id":"AMX_Ent_1436402","isEnterprise":"true","lastModified":{"$date":"2016-08-18T07:59:57.248Z"},"productType":"cloudpbx"}
{"_id":{"$oid":"5937b286421aa949b22107e3"},"active":true,"authorizedServices":{},"id":"AMX_Ent_1436968","isEnterprise":"true","lastModified":{"$date":"2016-08-18T07:59:57.248Z"},"productType":"cloudpbx"}
{"_id":{"$oid":"5937b2b9421aa949b2212395"},"active":true,"authorizedServices":{},"id":"Operadora Romano","isEnterprise":"true","lastModified":{"$date":"2016-08-18T08:00:26.009Z"},"productType":"cuad"}
{"_id":{"$oid":"5937b2bb421aa949b2212450"},"active":true,"authorizedServices":{},"id":"Presidencia_de_la_Republica","isEnterprise":"true","lastModified":{"$date":"2016-08-18T08:00:26.009Z"},"productType":"cuad"}
{"_id":{"$oid":"5937b315421aa949b2216e8e"},"active":true,"authorizedServices":{},"id":"AMX_Ent_1437825","isEnterprise":"true","lastModified":{"$date":"2016-08-21T08:02:19.296Z"},"productType":"cloudpbx"}
{"_id":{"$oid":"5937b3ad421aa949b221c4e0"},"active":true,"authorizedServices":{},"id":"AMX_Ent_1438057","isEnterprise":"true","lastModified":{"$date":"2016-08-22T08:04:51.016Z"},"productType":"cloudpbx"}
{"_id":{"$oid":"5937b456421aa949b22231c2"},"active":true,"authorizedServices":{},"id":"Demo_Conferencia","isEnterprise":"true","lastModified":{"$date":"2016-08-25T08:07:43.104Z"},"productType":"cuad"}
{"_id":{"$oid":"5937b45e421aa949b22233ca"},"active":true,"authorizedServices":{},"id":"Fundacion_Carlos_Slim","isEnterprise":"true","lastModified":{"$date":"2016-08-25T08:07:43.104Z"},"productType":"cuad"}
{"_id":{"$oid":"5937b4f2421aa949b22286dd"},"active":true,"authorizedServices":{},"id":"AMX_Ent_1439143","isEnterprise":"true","lastModified":{"$date":"2016-08-30T08:10:15.785Z"},"productType":"cloudpbx"}
{"_id":{"$oid":"5937b4f2421aa949b22286e8"},"active":true,"authorizedServices":{},"id":"AMX_Ent_1439325","isEnterprise":"true","lastModified":{"$date":"2016-08-30T08:10:15.785Z"},"productType":"cloudpbx"}
{"_id":{"$oid":"5937b4f2421aa949b22286f3"},"active":true,"authorizedServices":{},"id":"AMX_Ent_1439367","isEnterprise":"true","lastModified":{"$date":"2016-08-30T08:10:15.785Z"},"productType":"cloudpbx"}
{"_id":{"$oid":"5937b519421aa949b2229d8c"},"active":true,"authorizedServices":{},"id":"Gayosso","isEnterprise":"true","lastModified":{"$date":"2016-08-30T08:10:47.321Z"},"productType":"cuad"}
{"_id":{"$oid":"5937b61a421aa949b2231dce"},"active":false,"authorizedServices":{},"id":"Financiera Ayudamos","isEnterprise":"true","lastModified":{"$date":"2016-10-05T08:25:12.289Z"},"productType":"cuad"}
{"_id":{"$oid":"5937b67e421aa949b2236e47"},"active":false,"authorizedServices":{},"id":"larf","isEnterprise":"true","lastModified":{"$date":"2016-12-18T08:54:14.359Z"},"productType":"cuad"}
{"_id":{"$oid":"5937b843421aa949b2247930"},"active":true,"authorizedServices":{"attributes":[{"name":"maxTrunkGroupSimultaneousCalls","value":0}],"name":"TrunkGroup"},"id":"AMX_DEMO_1234567","isEnterprise":"true","lastModified":{"$date":"2016-10-05T08:24:34.593Z"},"productType":"cloudpbx"}
{"_id":{"$oid":"5937b844421aa949b2247992"},"active":true,"authorizedServices":{},"id":"AMX_Ent_1166601","isEnterprise":"true","lastModified":{"$date":"2016-10-05T08:24:34.593Z"},"productType":"cloudpbx"}
{"_id":{"$oid":"5937b84d421aa949b2247dd1"},"active":true,"authorizedServices":{},"id":"AMX_Ent_1441185","isEnterprise":"true","lastModified":{"$date":"2016-10-05T08:24:34.593Z"},"productType":"cloudpbx"}
{"_id":{"$oid":"5937b84d421aa949b2247e09"},"active":true,"authorizedServices":{},"id":"AMX_Ent_1443342","isEnterprise":"true","lastModified":{"$date":"2016-10-05T08:24:34.593Z"},"productType":"cloudpbx"}
{"_id":{"$oid":"5937b84d421aa949b2247e14"},"active":true,"authorizedServices":{},"id":"AMX_Ent_1443863","isEnterprise":"true","lastModified":{"$date":"2016-10-05T08:24:34.593Z"},"productType":"cloudpbx"}
{"_id":{"$oid":"5937b84d421aa949b2247e3a"},"active":true,"authorizedServices":{},"id":"AMX_Ent_1444530","isEnterprise":"true","lastModified":{"$date":"2016-10-05T08:24:34.593Z"},"productType":"cloudpbx"}
{"_id":{"$oid":"5937b84d421aa949b2247e45"},"active":false,"authorizedServices":{},"id":"AMX_Ent_1445014","isEnterprise":"true","lastModified":{"$date":"2017-12-07T08:00:04.001Z"},"productType":"cloudpbx"}
{"_id":{"$oid":"5937b84e421aa949b2247e59"},"active":true,"authorizedServices":{},"id":"AMX_Ent_1445185","isEnterprise":"true","lastModified":{"$date":"2016-10-05T08:24:34.593Z"},"productType":"cloudpbx"}
{"_id":{"$oid":"5937b879421aa949b224938c"},"active":true,"authorizedServices":{},"id":"Financiera_Ayudamos","isEnterprise":"true","lastModified":{"$date":"2016-10-05T08:25:12.289Z"},"productType":"cuad"}
{"_id":{"$oid":"5937ba57421aa949b2259698"},"active":true,"authorizedServices":{},"id":"SFGEBCS","isEnterprise":"true","lastModified":{"$date":"2016-10-23T08:32:38.590Z"},"productType":"cuad"}
{"_id":{"$oid":"5937bab9421aa949b225e17f"},"active":false,"authorizedServices":{},"id":"Delegacion_Miguel_Hidalgo","isEnterprise":"true","lastModified":{"$date":"2016-11-03T08:37:44.266Z"},"productType":"cuad"}
{"_id":{"$oid":"5937bb61421aa949b22636e9"},"active":true,"authorizedServices":{},"id":"DMH","isEnterprise":"true","lastModified":{"$date":"2016-11-03T08:37:44.266Z"},"productType":"cuad"}
{"_id":{"$oid":"5937bb64421aa949b2263794"},"active":false,"authorizedServices":{},"id":"FCI Administradora","isEnterprise":"true","lastModified":{"$date":"2016-11-08T08:40:32.058Z"},"productType":"cuad"}
{"_id":{"$oid":"5937bc0a421aa949b2268daa"},"active":true,"authorizedServices":{},"id":"FCI_Administradora","isEnterprise":"true","lastModified":{"$date":"2016-11-22T08:44:02.677Z"},"productType":"cuad"}
{"_id":{"$oid":"5937bcff421aa949b226ecfb"},"active":true,"authorizedServices":{},"id":"Safety_Textiles","isEnterprise":"true","lastModified":{"$date":"2016-11-22T08:44:02.677Z"},"productType":"cuad"}
{"_id":{"$oid":"5937bd81421aa949b2273ac3"},"active":true,"authorizedServices":{},"id":"AMX_Ent_1453097","isEnterprise":"true","lastModified":{"$date":"2016-12-04T08:46:44.558Z"},"productType":"cloudpbx"}
{"_id":{"$oid":"5937bd82421aa949b2273b14"},"active":true,"authorizedServices":{},"id":"AMX_Ent_1453551","isEnterprise":"true","lastModified":{"$date":"2016-12-04T08:46:44.558Z"},"productType":"cloudpbx"}
{"_id":{"$oid":"5937bd82421aa949b2273b35"},"active":true,"authorizedServices":{},"id":"AMX_Ent_1453891","isEnterprise":"true","lastModified":{"$date":"2016-12-04T08:46:44.558Z"},"productType":"cloudpbx"}
{"_id":{"$oid":"5937bd82421aa949b2273b40"},"active":false,"authorizedServices":{},"id":"AMX_Ent_1455757","isEnterprise":"true","lastModified":{"$date":"2017-10-10T07:00:04.083Z"},"productType":"cloudpbx"}
{"_id":{"$oid":"5937bd82421aa949b2273b62"},"active":false,"authorizedServices":{},"id":"AMX_Ent_1457957","isEnterprise":"true","lastModified":{"$date":"2018-02-20T08:00:03.539Z"},"productType":"cloudpbx"}
{"_id":{"$oid":"5937bd82421aa949b2273b7a"},"active":true,"authorizedServices":{},"id":"AMX_Ent_1458679","isEnterprise":"true","lastModified":{"$date":"2016-12-04T08:46:44.558Z"},"productType":"cloudpbx"}
{"_id":{"$oid":"5937bd82421aa949b2273ba0"},"active":true,"authorizedServices":{},"id":"AMX_Ent_1469542","isEnterprise":"true","lastModified":{"$date":"2016-12-04T08:46:44.558Z"},"productType":"cloudpbx"}
{"_id":{"$oid":"5937bd82421aa949b2273ba2"},"active":true,"authorizedServices":{},"id":"AMX_Ent_1469579","isEnterprise":"true","lastModified":{"$date":"2016-12-04T08:46:44.558Z"},"productType":"cloudpbx"}
{"_id":{"$oid":"5937bd82421aa949b2273bb6"},"active":true,"authorizedServices":{},"id":"AMX_Ent_1470678","isEnterprise":"true","lastModified":{"$date":"2016-12-04T08:46:44.558Z"},"productType":"cloudpbx"}
{"_id":{"$oid":"5937bd82421aa949b2273bc1"},"active":true,"authorizedServices":{},"id":"AMX_Ent_1475094","isEnterprise":"true","lastModified":{"$date":"2016-12-04T08:46:44.558Z"},"productType":"cloudpbx"}
{"_id":{"$oid":"5937bd82421aa949b2273bcc"},"active":true,"authorizedServices":{},"id":"AMX_Ent_1481397","isEnterprise":"true","lastModified":{"$date":"2016-12-04T08:46:44.558Z"},"productType":"cloudpbx"}
{"_id":{"$oid":"5937bd82421aa949b2273bd7"},"active":true,"authorizedServices":{},"id":"AMX_Ent_1486611","isEnterprise":"true","lastModified":{"$date":"2016-12-04T08:46:44.558Z"},"productType":"cloudpbx"}
{"_id":{"$oid":"5937bd82421aa949b2273be2"},"active":true,"authorizedServices":{},"id":"AMX_Ent_1491045","isEnterprise":"true","lastModified":{"$date":"2016-12-04T08:46:44.558Z"},"productType":"cloudpbx"}
{"_id":{"$oid":"5937bd82421aa949b2273bed"},"active":true,"authorizedServices":{},"id":"AMX_Ent_1491842","isEnterprise":"true","lastModified":{"$date":"2016-12-04T08:46:44.558Z"},"productType":"cloudpbx"}
{"_id":{"$oid":"5937bd82421aa949b2273bf8"},"active":true,"authorizedServices":{},"id":"AMX_Ent_1494561","isEnterprise":"true","lastModified":{"$date":"2016-12-04T08:46:44.558Z"},"productType":"cloudpbx"}
{"_id":{"$oid":"5937bd83421aa949b2273c03"},"active":true,"authorizedServices":{},"id":"AMX_Ent_1497624","isEnterprise":"true","lastModified":{"$date":"2016-12-04T08:46:44.558Z"},"productType":"cloudpbx"}
{"_id":{"$oid":"5937bd8b421aa949b2273cb8"},"active":true,"authorizedServices":{},"id":"AMX_Cloud_1105609","isEnterprise":"true","lastModified":{"$date":"2016-12-05T08:47:06.828Z"},"productType":"cloudpbx"}
{"_id":{"$oid":"5937be48421aa949b2276d95"},"active":true,"authorizedServices":{"attributes":[{"name":"maxTrunkGroupSimultaneousCalls","value":0}],"name":"TrunkGroup"},"id":"Licenciamiento","isEnterprise":"true","lastModified":{"$date":"2016-12-12T08:49:39.916Z"},"productType":"cuad"}
{"_id":{"$oid":"5937bf02421aa949b227cdf3"},"active":true,"authorizedServices":{},"id":"AMX_Ent_1515992","isEnterprise":"true","lastModified":{"$date":"2016-12-16T08:53:06.696Z"},"productType":"cloudpbx"}
{"_id":{"$oid":"5937bfed421aa949b2283779"},"active":true,"authorizedServices":{},"id":"AMX_Ent_1459220","isEnterprise":"true","lastModified":{"$date":"2016-12-20T08:57:02.470Z"},"productType":"cloudpbx"}
{"_id":{"$oid":"5937bfed421aa949b2283784"},"active":true,"authorizedServices":{},"id":"AMX_Ent_1469376","isEnterprise":"true","lastModified":{"$date":"2017-11-30T08:00:04.056Z"},"productType":"cloudpbx"}
{"_id":{"$oid":"5937bfee421aa949b22837a6"},"active":false,"authorizedServices":{},"id":"AMX_Ent_1519635","isEnterprise":"true","lastModified":{"$date":"2017-12-07T08:00:04.001Z"},"productType":"cloudpbx"}
{"_id":{"$oid":"5937c00f421aa949b2283edc"},"active":true,"authorizedServices":{},"id":"GVM","isEnterprise":"true","lastModified":{"$date":"2016-12-20T08:57:25.699Z"},"productType":"cuad"}
{"_id":{"$oid":"5937c0a8421aa949b22897ac"},"active":false,"authorizedServices":{},"id":"AMX_Ent_1523523","isEnterprise":"true","lastModified":{"$date":"2016-12-23T09:00:30.526Z"},"productType":"cloudpbx"}
{"_id":{"$oid":"5937c0a8421aa949b22897b7"},"active":false,"authorizedServices":{},"id":"AMX_Ent_1523524","isEnterprise":"true","lastModified":{"$date":"2016-12-23T09:00:30.526Z"},"productType":"cloudpbx"}
{"_id":{"$oid":"5937c1e7421aa949b228ef8c"},"active":true,"authorizedServices":{},"id":"Te_creemos","isEnterprise":"true","lastModified":{"$date":"2017-01-02T09:04:49.003Z"},"productType":"cuad"}
{"_id":{"$oid":"5937c264421aa949b2294226"},"active":false,"authorizedServices":{},"id":"AMX_Ent_1509891","isEnterprise":"true","lastModified":{"$date":"2017-10-20T07:00:03.734Z"},"productType":"cloudpbx"}
{"_id":{"$oid":"5937c2c2421aa949b2295b51"},"active":true,"authorizedServices":{},"id":"AMX_Ent_1535847","isEnterprise":"true","lastModified":{"$date":"2017-01-09T09:09:05.827Z"},"productType":"cloudpbx"}
{"_id":{"$oid":"5937c2c2421aa949b2295b5c"},"active":true,"authorizedServices":{},"id":"AMX_Ent_1535910","isEnterprise":"true","lastModified":{"$date":"2017-01-09T09:09:05.827Z"},"productType":"cloudpbx"}
{"_id":{"$oid":"5937c340421aa949b2297aac"},"active":true,"authorizedServices":{},"id":"ATP_Flecha_Roja","isEnterprise":"true","lastModified":{"$date":"2017-01-15T09:11:22.730Z"},"productType":"cuad"}
{"_id":{"$oid":"5937c361421aa949b2298436"},"active":true,"authorizedServices":{},"id":"LALA","isEnterprise":"true","lastModified":{"$date":"2017-01-15T09:11:22.730Z"},"productType":"cuad"}
{"_id":{"$oid":"5937c3f8421aa949b229ddf0"},"active":true,"authorizedServices":{},"id":"AMX_Ent_1542735","isEnterprise":"true","lastModified":{"$date":"2017-01-17T09:14:15.088Z"},"productType":"cloudpbx"}
{"_id":{"$oid":"5937c4b0421aa949b22a46aa"},"active":false,"authorizedServices":{},"id":"robustecimiento1","isEnterprise":"true","lastModified":{"$date":"2017-02-15T10:25:26.245Z"},"productType":"cuad"}
{"_id":{"$oid":"5937c565421aa949b22aacf8"},"active":false,"authorizedServices":{},"id":"robustecimiento2","isEnterprise":"true","lastModified":{"$date":"2017-02-15T10:25:26.245Z"},"productType":"cuad"}
{"_id":{"$oid":"5937cf26421aa949b22fdb4a"},"active":false,"authorizedServices":{},"id":"AMX_Ent_1088215","isEnterprise":"true","lastModified":{"$date":"2017-09-07T07:00:03.493Z"},"productType":"cloudpbx"}
{"_id":{"$oid":"5937cf41421aa949b22fe069"},"active":false,"authorizedServices":{},"id":"AMX_Ent_1564324","isEnterprise":"true","lastModified":{"$date":"2017-02-09T10:05:46.692Z"},"productType":"cloudpbx"}
{"_id":{"$oid":"5937cfd6421aa949b2303322"},"active":true,"authorizedServices":{},"id":"UANE","isEnterprise":"true","lastModified":{"$date":"2017-02-08T10:02:52.056Z"},"productType":"cuad"}
{"_id":{"$oid":"5937d00d421aa949b23047a4"},"active":false,"authorizedServices":{},"id":"AMX_Ent_1565928","isEnterprise":"true","lastModified":{"$date":"2017-02-10T10:08:55.467Z"},"productType":"cloudpbx"}
{"_id":{"$oid":"5937d00d421aa949b23047af"},"active":false,"authorizedServices":{},"id":"AMX_Ent_1566022","isEnterprise":"true","lastModified":{"$date":"2017-02-10T10:08:55.467Z"},"productType":"cloudpbx"}
{"_id":{"$oid":"5937d0c9421aa949b230b128"},"active":true,"authorizedServices":{},"id":"AMX_Ent_1567489","isEnterprise":"true","lastModified":{"$date":"2017-02-10T10:08:55.467Z"},"productType":"cloudpbx"}
{"_id":{"$oid":"5937d0c9421aa949b230b133"},"active":true,"authorizedServices":{},"id":"AMX_Ent_1567766","isEnterprise":"true","lastModified":{"$date":"2017-02-10T10:08:55.467Z"},"productType":"cloudpbx"}
{"_id":{"$oid":"5937d4a5421aa949b232cc4d"},"active":true,"authorizedServices":{},"id":"Ejemplo","isEnterprise":"true","lastModified":{"$date":"2017-02-15T10:25:26.245Z"},"productType":"cuad"}
{"_id":{"$oid":"5937d8de421aa949b234ddb9"},"active":true,"authorizedServices":{},"id":"Cometra","isEnterprise":"true","lastModified":{"$date":"2017-02-20T10:43:33.507Z"},"productType":"cuad"}
{"_id":{"$oid":"5937d8f4421aa949b234e31e"},"active":true,"authorizedServices":{},"id":"HCDG","isEnterprise":"true","lastModified":{"$date":"2017-02-20T10:43:33.507Z"},"productType":"cuad"}
{"_id":{"$oid":"5937d98a421aa949b2354057"},"active":false,"authorizedServices":{},"id":"AMX_Ent_1578580","isEnterprise":"true","lastModified":{"$date":"2017-02-23T10:52:36.719Z"},"productType":"cloudpbx"}
{"_id":{"$oid":"5937d98a421aa949b2354062"},"active":true,"authorizedServices":{},"id":"AMX_Ent_1578989","isEnterprise":"true","lastModified":{"$date":"2017-02-21T10:46:15.263Z"},"productType":"cloudpbx"}
{"_id":{"$oid":"5937d98a421aa949b235406d"},"active":false,"authorizedServices":{},"id":"AMX_Ent_1579053","isEnterprise":"true","lastModified":{"$date":"2017-02-23T10:52:36.719Z"},"productType":"cloudpbx"}
{"_id":{"$oid":"5937d9a9421aa949b2354b22"},"active":true,"authorizedServices":{},"id":"Fidere_III","isEnterprise":"true","lastModified":{"$date":"2017-02-21T10:46:43.968Z"},"productType":"cuad"}
{"_id":{"$oid":"5937d9b6421aa949b2354f60"},"active":true,"authorizedServices":{},"id":"INFONAVIT","isEnterprise":"true","lastModified":{"$date":"2017-02-21T10:46:43.968Z"},"productType":"cuad"}
{"_id":{"$oid":"5937da45421aa949b235aacd"},"active":true,"authorizedServices":{},"id":"AMX_Ent_1580607","isEnterprise":"true","lastModified":{"$date":"2017-02-22T10:49:21.310Z"},"productType":"cloudpbx"}
{"_id":{"$oid":"5937da45421aa949b235aad8"},"active":false,"authorizedServices":{},"id":"AMX_Ent_1580636","isEnterprise":"true","lastModified":{"$date":"2017-02-28T11:09:57.899Z"},"productType":"cloudpbx"}
{"_id":{"$oid":"5937da45421aa949b235aae3"},"active":false,"authorizedServices":{},"id":"AMX_Ent_1580662","isEnterprise":"true","lastModified":{"$date":"2017-02-28T11:09:57.899Z"},"productType":"cloudpbx"}
{"_id":{"$oid":"5937db06421aa949b23615ba"},"active":true,"authorizedServices":{},"id":"AMX_Ent_1523744","isEnterprise":"true","lastModified":{"$date":"2017-02-23T10:52:36.719Z"},"productType":"cloudpbx"}
{"_id":{"$oid":"5937dbd4421aa949b23682b3"},"active":true,"authorizedServices":{},"id":"AMX_Ent_1585276","isEnterprise":"true","lastModified":{"$date":"2017-02-24T10:56:00.347Z"},"productType":"cloudpbx"}
{"_id":{"$oid":"5937dbd4421aa949b23682be"},"active":true,"authorizedServices":{},"id":"AMX_Ent_1585406","isEnterprise":"true","lastModified":{"$date":"2017-02-24T10:56:00.347Z"},"productType":"cloudpbx"}
{"_id":{"$oid":"5937df1a421aa949b2382942"},"active":true,"authorizedServices":{},"id":"AMX_Ent_1587469","isEnterprise":"true","lastModified":{"$date":"2017-02-28T11:09:57.899Z"},"productType":"cloudpbx"}
{"_id":{"$oid":"5937df1a421aa949b2382956"},"active":false,"authorizedServices":{},"id":"AMX_Ent_1587498","isEnterprise":"true","lastModified":{"$date":"2017-03-02T11:16:15.602Z"},"productType":"cloudpbx"}
{"_id":{"$oid":"5937dfd8421aa949b2389369"},"active":true,"authorizedServices":{},"id":"AMX_Ent_1590722","isEnterprise":"true","lastModified":{"$date":"2017-03-01T11:13:09.477Z"},"productType":"cloudpbx"}
{"_id":{"$oid":"5937dfd8421aa949b2389374"},"active":true,"authorizedServices":{},"id":"AMX_Ent_1590763","isEnterprise":"true","lastModified":{"$date":"2017-03-01T11:13:09.477Z"},"productType":"cloudpbx"}
{"_id":{"$oid":"5937e092421aa949b238fd9d"},"active":false,"authorizedServices":{},"id":"AMX_Ent_1591735","isEnterprise":"true","lastModified":{"$date":"2017-03-07T11:32:57.361Z"},"productType":"cloudpbx"}
{"_id":{"$oid":"5937e153421aa949b239696d"},"active":true,"authorizedServices":{},"id":"AMX_Ent_1592720","isEnterprise":"true","lastModified":{"$date":"2017-03-03T11:19:25.441Z"},"productType":"cloudpbx"}
{"_id":{"$oid":"5937e153421aa949b2396978"},"active":true,"authorizedServices":{},"id":"AMX_Ent_1592741","isEnterprise":"true","lastModified":{"$date":"2017-03-03T11:19:25.441Z"},"productType":"cloudpbx"}
{"_id":{"$oid":"5937e153421aa949b2396983"},"active":true,"authorizedServices":{},"id":"AMX_Ent_1593523","isEnterprise":"true","lastModified":{"$date":"2017-03-03T11:19:25.441Z"},"productType":"cloudpbx"}
{"_id":{"$oid":"5937e153421aa949b239698e"},"active":true,"authorizedServices":{},"id":"AMX_Ent_1594702","isEnterprise":"true","lastModified":{"$date":"2017-03-03T11:19:25.441Z"},"productType":"cloudpbx"}
{"_id":{"$oid":"5937e3a7421aa949b23aa977"},"active":true,"authorizedServices":{},"id":"AMX_Ent_1596240","isEnterprise":"true","lastModified":{"$date":"2017-03-06T11:29:21.335Z"},"productType":"cloudpbx"}
{"_id":{"$oid":"5937e3a7421aa949b23aa982"},"active":true,"authorizedServices":{},"id":"AMX_Ent_1596247","isEnterprise":"true","lastModified":{"$date":"2017-03-06T11:29:21.335Z"},"productType":"cloudpbx"}
{"_id":{"$oid":"5937e480421aa949b23b148e"},"active":false,"authorizedServices":{},"id":"AMX_Ent_1597111","isEnterprise":"true","lastModified":{"$date":"2017-03-08T11:36:36.887Z"},"productType":"cloudpbx"}
{"_id":{"$oid":"5937e55a421aa949b23b7fe1"},"active":true,"authorizedServices":{},"id":"AMX_Ent_1598308","isEnterprise":"true","lastModified":{"$date":"2017-03-08T11:36:36.887Z"},"productType":"cloudpbx"}
{"_id":{"$oid":"5937e55a421aa949b23b7fec"},"active":false,"authorizedServices":{},"id":"AMX_Ent_1599870","isEnterprise":"true","lastModified":{"$date":"2018-04-23T07:00:02.903Z"},"productType":"cloudpbx"}
{"_id":{"$oid":"5937e6f4421aa949b23c5717"},"active":false,"authorizedServices":{},"id":"AMX_Ent_1604006","isEnterprise":"true","lastModified":{"$date":"2017-03-24T12:28:07.953Z"},"productType":"cloudpbx"}
{"_id":{"$oid":"5937e6f4421aa949b23c5722"},"active":false,"authorizedServices":{},"id":"AMX_Ent_1604040","isEnterprise":"true","lastModified":{"$date":"2017-03-24T12:28:07.953Z"},"productType":"cloudpbx"}
{"_id":{"$oid":"5937e6f4421aa949b23c572d"},"active":false,"authorizedServices":{},"id":"AMX_Ent_1604063","isEnterprise":"true","lastModified":{"$date":"2017-03-24T12:28:07.953Z"},"productType":"cloudpbx"}
{"_id":{"$oid":"5937e6f4421aa949b23c5738"},"active":false,"authorizedServices":{},"id":"AMX_Ent_1604100","isEnterprise":"true","lastModified":{"$date":"2017-03-24T12:28:07.953Z"},"productType":"cloudpbx"}
{"_id":{"$oid":"5937e6f5421aa949b23c5743"},"active":false,"authorizedServices":{},"id":"AMX_Ent_1604119","isEnterprise":"true","lastModified":{"$date":"2017-03-24T12:28:07.953Z"},"productType":"cloudpbx"}
{"_id":{"$oid":"5937e6f5421aa949b23c574e"},"active":false,"authorizedServices":{},"id":"AMX_Ent_1604156","isEnterprise":"true","lastModified":{"$date":"2017-03-24T12:28:07.953Z"},"productType":"cloudpbx"}
{"_id":{"$oid":"5937e6f5421aa949b23c5759"},"active":false,"authorizedServices":{},"id":"AMX_Ent_1604177","isEnterprise":"true","lastModified":{"$date":"2017-03-24T12:28:07.953Z"},"productType":"cloudpbx"}
{"_id":{"$oid":"5937e6f5421aa949b23c5764"},"active":false,"authorizedServices":{},"id":"AMX_Ent_1604199","isEnterprise":"true","lastModified":{"$date":"2017-03-24T12:28:07.953Z"},"productType":"cloudpbx"}
{"_id":{"$oid":"5937e6f5421aa949b23c576f"},"active":false,"authorizedServices":{},"id":"AMX_Ent_1604217","isEnterprise":"true","lastModified":{"$date":"2017-03-24T12:28:07.953Z"},"productType":"cloudpbx"}
{"_id":{"$oid":"5937e6f5421aa949b23c577a"},"active":false,"authorizedServices":{},"id":"AMX_Ent_1604235","isEnterprise":"true","lastModified":{"$date":"2017-03-24T12:28:07.953Z"},"productType":"cloudpbx"}
{"_id":{"$oid":"5937e93b421aa949b23d9ac1"},"active":true,"authorizedServices":{},"id":"AMX_Ent_1605827","isEnterprise":"true","lastModified":{"$date":"2017-03-13T11:53:11.661Z"},"productType":"cloudpbx"}
{"_id":{"$oid":"5937e93b421aa949b23d9acc"},"active":true,"authorizedServices":{},"id":"AMX_Ent_1605838","isEnterprise":"true","lastModified":{"$date":"2017-03-13T11:53:11.661Z"},"productType":"cloudpbx"}
{"_id":{"$oid":"5937e93b421aa949b23d9ad7"},"active":false,"authorizedServices":{},"id":"AMX_Ent_1605887","isEnterprise":"true","lastModified":{"$date":"2017-03-14T11:56:29.557Z"},"productType":"cloudpbx"}
{"_id":{"$oid":"5937e93b421aa949b23d9ae2"},"active":false,"authorizedServices":{},"id":"AMX_Ent_1605902","isEnterprise":"true","lastModified":{"$date":"2017-03-14T11:56:29.557Z"},"productType":"cloudpbx"}
{"_id":{"$oid":"5937ea04421aa949b23e0706"},"active":false,"authorizedServices":{},"id":"AMX_Ent_1608184","isEnterprise":"true","lastModified":{"$date":"2017-03-15T11:59:52.915Z"},"productType":"cloudpbx"}
{"_id":{"$oid":"5937ea04421aa949b23e0711"},"active":false,"authorizedServices":{},"id":"AMX_Ent_1608185","isEnterprise":"true","lastModified":{"$date":"2017-03-15T11:59:52.915Z"},"productType":"cloudpbx"}
{"_id":{"$oid":"5937ea3e421aa949b23e1b4e"},"active":true,"authorizedServices":{},"id":"Lideres_SIO","isEnterprise":"true","lastModified":{"$date":"2017-03-14T11:57:03.176Z"},"productType":"cuad"}
{"_id":{"$oid":"5937ec7b421aa949b23f4cab"},"active":false,"authorizedServices":{},"id":"AMX_Ent_1534666","isEnterprise":"true","lastModified":{"$date":"2017-08-24T07:00:03.434Z"},"productType":"cloudpbx"}
{"_id":{"$oid":"5937ec7d421aa949b23f4d3e"},"active":true,"authorizedServices":{},"id":"AMX_Ent_1607946","isEnterprise":"true","lastModified":{"$date":"2017-03-17T12:07:03.655Z"},"productType":"cloudpbx"}
{"_id":{"$oid":"5937ec7d421aa949b23f4d49"},"active":true,"authorizedServices":{},"id":"AMX_Ent_1611915","isEnterprise":"true","lastModified":{"$date":"2017-03-17T12:07:03.655Z"},"productType":"cloudpbx"}
{"_id":{"$oid":"5937eeff421aa949b2409e40"},"active":false,"authorizedServices":{},"id":"AMX_Ent_1614479","isEnterprise":"true","lastModified":{"$date":"2017-03-22T12:21:09.459Z"},"productType":"cloudpbx"}
{"_id":{"$oid":"5937f16e421aa949b241e4f5"},"active":true,"authorizedServices":{},"id":"AMX_Ent_1621305","isEnterprise":"true","lastModified":{"$date":"2017-03-24T12:28:07.953Z"},"productType":"cloudpbx"}
{"_id":{"$oid":"5937f501421aa949b2439792"},"active":false,"authorizedServices":{},"id":"AMX_Ent_1624385","isEnterprise":"true","lastModified":{"$date":"2017-04-08T13:22:50.410Z"},"productType":"cloudpbx"}
{"_id":{"$oid":"5937f515421aa949b2439f47"},"active":true,"authorizedServices":{},"id":"CEM","isEnterprise":"true","lastModified":{"$date":"2017-03-28T12:43:56.685Z"},"productType":"cuad"}
{"_id":{"$oid":"5937f534421aa949b243a783"},"active":true,"authorizedServices":{},"id":"JEC","isEnterprise":"true","lastModified":{"$date":"2017-03-28T12:43:56.685Z"},"productType":"cuad"}
{"_id":{"$oid":"5937f5d0421aa949b24403c8"},"active":false,"authorizedServices":{},"id":"AMX_Ent_1625587","isEnterprise":"true","lastModified":{"$date":"2017-04-07T13:19:02.364Z"},"productType":"cloudpbx"}
{"_id":{"$oid":"5937f5d0421aa949b24403d3"},"active":true,"authorizedServices":{},"id":"AMX_Ent_1625734","isEnterprise":"true","lastModified":{"$date":"2017-03-29T12:46:50.163Z"},"productType":"cloudpbx"}
{"_id":{"$oid":"5937f698421aa949b2447033"},"active":false,"authorizedServices":{},"id":"AMX_Ent_1629105","isEnterprise":"true","lastModified":{"$date":"2017-04-08T13:22:50.410Z"},"productType":"cloudpbx"}
{"_id":{"$oid":"5937f698421aa949b244703e"},"active":true,"authorizedServices":{},"id":"AMX_Ent_1629160","isEnterprise":"true","lastModified":{"$date":"2017-03-30T12:50:10.593Z"},"productType":"cloudpbx"}
{"_id":{"$oid":"5937f698421aa949b2447049"},"active":true,"authorizedServices":{},"id":"AMX_Ent_1629162","isEnterprise":"true","lastModified":{"$date":"2017-03-30T12:50:10.593Z"},"productType":"cloudpbx"}
{"_id":{"$oid":"5937f698421aa949b2447054"},"active":false,"authorizedServices":{},"id":"AMX_Ent_1629172","isEnterprise":"true","lastModified":{"$date":"2017-04-07T13:19:02.364Z"},"productType":"cloudpbx"}
{"_id":{"$oid":"5937f698421aa949b244705f"},"active":true,"authorizedServices":{},"id":"AMX_Ent_1629176","isEnterprise":"true","lastModified":{"$date":"2017-03-30T12:50:10.593Z"},"productType":"cloudpbx"}
{"_id":{"$oid":"5937f698421aa949b244706a"},"active":true,"authorizedServices":{},"id":"AMX_Ent_1629182","isEnterprise":"true","lastModified":{"$date":"2017-03-30T12:50:10.593Z"},"productType":"cloudpbx"}
{"_id":{"$oid":"5937f6d6421aa949b2448694"},"active":false,"authorizedServices":{},"id":"MMT","isEnterprise":"true","lastModified":{"$date":"2017-08-17T07:00:52.318Z"},"productType":"cuad"}
{"_id":{"$oid":"5937f6e4421aa949b2448a6a"},"active":false,"authorizedServices":{},"id":"PGJ","isEnterprise":"true","lastModified":{"$date":"2017-04-07T13:19:35.256Z"},"productType":"cuad"}
{"_id":{"$oid":"5937f76b421aa949b244de9e"},"active":false,"authorizedServices":{},"id":"AMX_Ent_1629553","isEnterprise":"true","lastModified":{"$date":"2017-04-07T13:19:02.364Z"},"productType":"cloudpbx"}
{"_id":{"$oid":"5937f76b421aa949b244dea9"},"active":true,"authorizedServices":{},"id":"AMX_Ent_1629576","isEnterprise":"true","lastModified":{"$date":"2017-03-31T12:53:40.342Z"},"productType":"cloudpbx"}
{"_id":{"$oid":"5937f76b421aa949b244deb4"},"active":true,"authorizedServices":{},"id":"AMX_Ent_1629592","isEnterprise":"true","lastModified":{"$date":"2017-03-31T12:53:40.342Z"},"productType":"cloudpbx"}
{"_id":{"$oid":"5937f76b421aa949b244debf"},"active":false,"authorizedServices":{},"id":"AMX_Ent_1629642","isEnterprise":"true","lastModified":{"$date":"2017-04-07T13:19:02.364Z"},"productType":"cloudpbx"}
{"_id":{"$oid":"5937f76b421aa949b244deca"},"active":true,"authorizedServices":{},"id":"AMX_Ent_1629666","isEnterprise":"true","lastModified":{"$date":"2017-03-31T12:53:40.342Z"},"productType":"cloudpbx"}
{"_id":{"$oid":"5937f76b421aa949b244ded5"},"active":false,"authorizedServices":{},"id":"AMX_Ent_1630011","isEnterprise":"true","lastModified":{"$date":"2017-04-08T13:22:50.410Z"},"productType":"cloudpbx"}
{"_id":{"$oid":"5937fa06421aa949b2462d9b"},"active":true,"authorizedServices":{},"id":"CGT","isEnterprise":"true","lastModified":{"$date":"2017-04-03T13:04:59.571Z"},"productType":"cuad"}
{"_id":{"$oid":"5937fa0d421aa949b2462f50"},"active":true,"authorizedServices":{},"id":"FOVISEC","isEnterprise":"true","lastModified":{"$date":"2017-04-03T13:04:59.571Z"},"productType":"cuad"}
{"_id":{"$oid":"5937fa3f421aa949b2463fd1"},"active":true,"authorizedServices":{},"id":"SESESP","isEnterprise":"true","lastModified":{"$date":"2017-04-03T13:04:59.571Z"},"productType":"cuad"}
{"_id":{"$oid":"5937facd421aa949b2469368"},"active":true,"authorizedServices":{},"id":"AMX_Ent_1632634","isEnterprise":"true","lastModified":{"$date":"2017-04-04T13:07:59.191Z"},"productType":"cloudpbx"}
{"_id":{"$oid":"5937facd421aa949b2469373"},"active":true,"authorizedServices":{},"id":"AMX_Ent_1632649","isEnterprise":"true","lastModified":{"$date":"2017-04-04T13:07:59.191Z"},"productType":"cloudpbx"}
{"_id":{"$oid":"5937facd421aa949b246937e"},"active":true,"authorizedServices":{},"id":"AMX_Ent_1632658","isEnterprise":"true","lastModified":{"$date":"2017-04-04T13:07:59.191Z"},"productType":"cloudpbx"}
{"_id":{"$oid":"5937facd421aa949b2469389"},"active":true,"authorizedServices":{},"id":"AMX_Ent_1632676","isEnterprise":"true","lastModified":{"$date":"2017-04-04T13:07:59.191Z"},"productType":"cloudpbx"}
{"_id":{"$oid":"5937facd421aa949b2469394"},"active":true,"authorizedServices":{},"id":"AMX_Ent_1632690","isEnterprise":"true","lastModified":{"$date":"2017-04-04T13:07:59.191Z"},"productType":"cloudpbx"}
{"_id":{"$oid":"5938020f421aa949b24a0cf0"},"active":true,"authorizedServices":{},"id":"AMX_Ent_1643956","isEnterprise":"true","lastModified":{"$date":"2017-04-12T13:39:04.046Z"},"productType":"cloudpbx"}
{"_id":{"$oid":"5938079d421aa949b24cb78b"},"active":true,"authorizedServices":{},"id":"H_TSJET","isEnterprise":"true","lastModified":{"$date":"2017-04-18T14:02:01.854Z"},"productType":"cuad"}
{"_id":{"$oid":"593808c4421aa949b24d1785"},"active":true,"authorizedServices":{},"id":"AMX_Ent_1651003","isEnterprise":"true","lastModified":{"$date":"2017-04-19T14:07:43.177Z"},"productType":"cloudpbx"}
{"_id":{"$oid":"59380d28421aa949b24f3e04"},"active":true,"authorizedServices":{},"id":"AMX_Ent_1655484","isEnterprise":"true","lastModified":{"$date":"2017-04-24T14:26:25.154Z"},"productType":"cloudpbx"}
{"_id":{"$oid":"59380d84421aa949b24f5a23"},"active":true,"authorizedServices":{},"id":"PGJ_MICH","isEnterprise":"true","lastModified":{"$date":"2017-04-24T14:27:00.134Z"},"productType":"cuad"}
{"_id":{"$oid":"593814ad421aa949b252b740"},"active":false,"authorizedServices":{},"id":"AMX_Ent_1665833","isEnterprise":"true","lastModified":{"$date":"2017-05-11T15:34:50.655Z"},"productType":"cloudpbx"}
{"_id":{"$oid":"59381d32421aa949b2569275"},"active":false,"authorizedServices":{},"id":"AMX_Ent_1676675","isEnterprise":"true","lastModified":{"$date":"2017-05-12T15:38:46.013Z"},"productType":"cloudpbx"}
{"_id":{"$oid":"59381d32421aa949b2569299"},"active":true,"authorizedServices":{},"id":"AMX_Ent_1677047","isEnterprise":"true","lastModified":{"$date":"2017-05-11T15:34:50.655Z"},"productType":"cloudpbx"}
{"_id":{"$oid":"593821f0421aa949b258c93d"},"active":true,"authorizedServices":{},"id":"AMX_Ent_1081542","isEnterprise":"true","lastModified":{"$date":"2017-05-16T15:55:27.639Z"},"productType":"cloudpbx"}
{"_id":{"$oid":"593821f2421aa949b258c9a6"},"active":true,"authorizedServices":{},"id":"AMX_Ent_1213595","isEnterprise":"true","lastModified":{"$date":"2017-05-16T15:55:27.639Z"},"productType":"cloudpbx"}
{"_id":{"$oid":"59382208421aa949b258cfb2"},"active":true,"authorizedServices":{},"id":"AMX_Ent_1682242","isEnterprise":"true","lastModified":{"$date":"2017-05-16T15:55:27.639Z"},"productType":"cloudpbx"}
{"_id":{"$oid":"59382413421aa949b259bd92"},"active":true,"authorizedServices":{},"id":"AMX_Ent_1686686","isEnterprise":"true","lastModified":{"$date":"2017-05-18T16:04:11.108Z"},"productType":"cloudpbx"}
{"_id":{"$oid":"59382803421aa949b25b9a46"},"active":true,"authorizedServices":{},"id":"AMX_Ent_1690367","isEnterprise":"true","lastModified":{"$date":"2017-05-22T16:20:57.889Z"},"productType":"cloudpbx"}
{"_id":{"$oid":"59382a02421aa949b25c8978"},"active":true,"authorizedServices":{},"id":"AMX_Ent_1685113","isEnterprise":"true","lastModified":{"$date":"2017-11-30T08:00:04.056Z"},"productType":"cloudpbx"}
{"_id":{"$oid":"593a478b421aa97df793e81f"},"active":true,"authorizedServices":{},"id":"AMX_Ent_1719206","isEnterprise":"true","lastModified":{"$date":"2017-06-08T07:00:03.976Z"},"productType":"cloudpbx"}
{"_id":{"$oid":"593f8d8b421aa93bb8a4c09b"},"active":true,"authorizedServices":{},"id":"AMX_Ent_1725819","isEnterprise":"true","lastModified":{"$date":"2017-11-30T08:00:04.056Z"},"productType":"cloudpbx"}
{"_id":{"$oid":"593f8d95421aa93bb8a4c62b"},"active":true,"authorizedServices":{},"id":"Emmariel_GT","isEnterprise":"true","lastModified":{"$date":"2017-06-12T07:00:28.708Z"},"productType":"uc"}
{"_id":{"$oid":"5940df12421aa931c1cc5428"},"active":true,"authorizedServices":{},"id":"AMX_Ent_1720207","isEnterprise":"true","lastModified":{"$date":"2017-06-13T07:00:09.106Z"},"productType":"cloudpbx"}
{"_id":{"$oid":"5940df12421aa931c1cc5434"},"active":true,"authorizedServices":{},"id":"AMX_Ent_1728285","isEnterprise":"true","lastModified":{"$date":"2017-06-13T07:00:09.106Z"},"productType":"cloudpbx"}
{"_id":{"$oid":"5942308c421aa925979a81f2"},"active":false,"authorizedServices":{},"id":"AMX_Ent_1729961","isEnterprise":"true","lastModified":{"$date":"2017-06-15T07:00:03.895Z"},"productType":"cloudpbx"}
{"_id":{"$oid":"5944d38d421aa90731b78666"},"active":false,"authorizedServices":{},"id":"AMX_Ent_1737793","isEnterprise":"true","lastModified":{"$date":"2017-09-15T07:00:08.421Z"},"productType":"cloudpbx"}
{"_id":{"$oid":"594a1a2d421aa94a2e2ed0a9"},"active":true,"authorizedServices":{},"id":"Super_Q","isEnterprise":"true","lastModified":{"$date":"2017-06-20T07:00:45.249Z"},"productType":"cuad"}
{"_id":{"$oid":"594e0e0f421aa9238cbfb6a0"},"active":false,"authorizedServices":{},"id":"AMX_Ent_1749880","isEnterprise":"true","lastModified":{"$date":"2017-08-31T07:00:03.872Z"},"productType":"cloudpbx"}
{"_id":{"$oid":"594e0e32421aa9238cbfc157"},"active":true,"authorizedServices":{},"id":"DURAPLAY","isEnterprise":"true","lastModified":{"$date":"2017-06-23T07:00:43.952Z"},"productType":"cuad"}
{"_id":{"$oid":"595202ff421aa971ca874208"},"active":true,"authorizedServices":{},"id":"KAA","isEnterprise":"true","lastModified":{"$date":"2017-06-26T07:00:47.983Z"},"productType":"cuad"}
{"_id":{"$oid":"5953540e421aa9639b80b875"},"active":true,"authorizedServices":{},"id":"AMX_Ent_1754265","isEnterprise":"true","lastModified":{"$date":"2017-06-27T07:00:03.378Z"},"productType":"cloudpbx"}
{"_id":{"$oid":"59574890421aa92e385b4389"},"active":true,"authorizedServices":{},"id":"AMX_Ent_1716779","isEnterprise":"true","lastModified":{"$date":"2017-06-30T07:00:03.805Z"},"productType":"cloudpbx"}
{"_id":{"$oid":"595b3d0e421aa97ad3c88456"},"active":true,"authorizedServices":{},"id":"AMX_Ent_1765558","isEnterprise":"true","lastModified":{"$date":"2017-07-03T07:00:03.284Z"},"productType":"cloudpbx"}
{"_id":{"$oid":"595c8e91421aa96f680b9e41"},"active":true,"authorizedServices":{},"id":"AMX_Ent_1640761","isEnterprise":"true","lastModified":{"$date":"2017-07-04T07:00:08.565Z"},"productType":"cloudpbx"}
{"_id":{"$oid":"595c8eb0421aa96f680ba656"},"active":true,"authorizedServices":{},"id":"BIMBO","isEnterprise":"true","lastModified":{"$date":"2017-07-04T07:00:49.819Z"},"productType":"cuad"}
{"_id":{"$oid":"595f3191421aa9578f0d43fd"},"active":true,"authorizedServices":{},"id":"AMX_Ent_1751480","isEnterprise":"true","lastModified":{"$date":"2017-07-06T07:00:03.672Z"},"productType":"cloudpbx"}
{"_id":{"$oid":"595f3191421aa9578f0d441b"},"active":true,"authorizedServices":{},"id":"AMX_Ent_1772020","isEnterprise":"true","lastModified":{"$date":"2017-07-06T07:00:03.672Z"},"productType":"cloudpbx"}
{"_id":{"$oid":"595f3192421aa9578f0d4426"},"active":true,"authorizedServices":{},"id":"AMX_Ent_1772869","isEnterprise":"true","lastModified":{"$date":"2017-07-06T07:00:03.672Z"},"productType":"cloudpbx"}
{"_id":{"$oid":"59608312421aa9457b933002"},"active":true,"authorizedServices":{},"id":"AMX_Ent_1772760","isEnterprise":"true","lastModified":{"$date":"2017-07-07T07:00:03.324Z"},"productType":"cloudpbx"}
{"_id":{"$oid":"5965c9de421aa91664f65961"},"active":true,"authorizedServices":{},"id":"STM","isEnterprise":"true","lastModified":{"$date":"2017-07-11T07:00:46.348Z"},"productType":"cuad"}
{"_id":{"$oid":"59671a90421aa911f38a47ca"},"active":true,"authorizedServices":{},"id":"AMX_Ent_1783002","isEnterprise":"true","lastModified":{"$date":"2017-07-12T07:00:03.544Z"},"productType":"cloudpbx"}
{"_id":{"$oid":"59705511421aa92f06709032"},"active":false,"authorizedServices":{},"id":"AMX_Ent_1795928","isEnterprise":"true","lastModified":{"$date":"2018-01-26T08:00:03.229Z"},"productType":"cloudpbx"}
{"_id":{"$oid":"5971a686421aa91f05e4b54b"},"active":true,"authorizedServices":{},"id":"AMX_Ent_1453754","isEnterprise":"true","lastModified":{"$date":"2017-07-20T07:00:03.362Z"},"productType":"cloudpbx"}
{"_id":{"$oid":"59783e13421aa946efe07344"},"active":true,"authorizedServices":{},"id":"AMX_Ent_1764741","isEnterprise":"true","lastModified":{"$date":"2017-07-25T07:00:04.239Z"},"productType":"cloudpbx"}
{"_id":{"$oid":"59783ee4421aa946efe0a192"},"active":true,"authorizedServices":{},"id":"PROCONSA","isEnterprise":"true","lastModified":{"$date":"2017-07-25T07:00:50.061Z"},"productType":"cuad"}
{"_id":{"$oid":"59798f93421aa936f3e8a079"},"active":true,"authorizedServices":{},"id":"AMX_Ent_1810451","isEnterprise":"true","lastModified":{"$date":"2017-07-26T07:00:03.688Z"},"productType":"cloudpbx"}
{"_id":{"$oid":"59802766620ece20fb0f6c29"},"active":true,"authorizedServices":{},"id":"GFC","isEnterprise":"true","lastModified":{"$date":"2017-07-31T07:00:48.924Z"},"productType":"cuad"}
{"_id":{"$oid":"598178bd620ece10f59a2cad"},"active":true,"authorizedServices":{},"id":"DOP","isEnterprise":"true","lastModified":{"$date":"2017-08-01T07:00:51.074Z"},"productType":"cuad"}
{"_id":{"$oid":"5982c9f8620ece0160cde5d3"},"active":true,"authorizedServices":{},"id":"AMX_Ent_1382476","isEnterprise":"true","lastModified":{"$date":"2017-08-02T07:00:03.395Z"},"productType":"cloudpbx"}
{"_id":{"$oid":"59841b94620ece720b9805c4"},"active":true,"authorizedServices":{},"id":"AMX_Ent_1810638","isEnterprise":"true","lastModified":{"$date":"2017-08-03T07:00:03.707Z"},"productType":"cloudpbx"}
{"_id":{"$oid":"598d5615620ece02e094f716"},"active":true,"authorizedServices":{},"id":"AMX_Ent_1834783","isEnterprise":"true","lastModified":{"$date":"2017-08-10T07:00:03.553Z"},"productType":"cloudpbx"}
{"_id":{"$oid":"59929c15620ece423f5fa627"},"active":false,"authorizedServices":{},"id":"AMX_Ent_1838163","isEnterprise":"true","lastModified":{"$date":"2017-10-09T07:00:04.109Z"},"productType":"cloudpbx"}
{"_id":{"$oid":"5993ed9b620ece33b1db9a1c"},"active":true,"authorizedServices":{},"id":"AMX_Ent_1841802","isEnterprise":"true","lastModified":{"$date":"2017-08-15T07:00:09.067Z"},"productType":"cloudpbx"}
{"_id":{"$oid":"59953f0f620ece243e8a5453"},"active":true,"authorizedServices":{},"id":"AMX_Ent_1566112","isEnterprise":"true","lastModified":{"$date":"2017-08-16T07:00:03.659Z"},"productType":"cloudpbx"}
{"_id":{"$oid":"5997e27f620ece03824b4883"},"active":false,"authorizedServices":{},"id":"HAVAS","isEnterprise":"true","lastModified":{"$date":"2017-08-22T07:00:58.248Z"},"productType":"cuad"}
{"_id":{"$oid":"599d2817620ece40bb918ca9"},"active":true,"authorizedServices":{},"id":"AMX_Ent_1854463","isEnterprise":"true","lastModified":{"$date":"2017-08-22T07:00:03.434Z"},"productType":"cloudpbx"}
{"_id":{"$oid":"599d2817620ece40bb918cbd"},"active":true,"authorizedServices":{},"id":"AMX_Ent_1854586","isEnterprise":"true","lastModified":{"$date":"2017-08-22T07:00:03.434Z"},"productType":"cloudpbx"}
{"_id":{"$oid":"599d287d620ece40bb919f6c"},"active":true,"authorizedServices":{},"id":"GVE","isEnterprise":"true","lastModified":{"$date":"2017-08-22T07:00:58.248Z"},"productType":"cuad"}
{"_id":{"$oid":"599fcb0d620ece1ee03f2cce"},"active":true,"authorizedServices":{},"id":"AMX_Ent_1512046","isEnterprise":"true","lastModified":{"$date":"2017-08-24T07:00:03.434Z"},"productType":"cloudpbx"}
{"_id":{"$oid":"59a7b439620ece384b306047"},"active":true,"authorizedServices":{},"id":"CAPOME","isEnterprise":"true","lastModified":{"$date":"2017-08-30T07:00:54.803Z"},"productType":"cuad"}
{"_id":{"$oid":"59a90598620ece27625ced7c"},"active":true,"authorizedServices":{},"id":"AMX_Ent_1867921","isEnterprise":"true","lastModified":{"$date":"2017-08-31T07:00:03.872Z"},"productType":"cloudpbx"}
{"_id":{"$oid":"59ae4bda620ece6289bde639"},"active":true,"authorizedServices":{},"id":"EME","isEnterprise":"true","lastModified":{"$date":"2017-09-04T07:00:55.935Z"},"productType":"cuad"}
{"_id":{"$oid":"59af9d58620ece51c0d0dac2"},"active":true,"authorizedServices":{},"id":"Dextra_TECH","isEnterprise":"true","lastModified":{"$date":"2017-09-05T07:00:55.627Z"},"productType":"cuad"}
{"_id":{"$oid":"59af9db9620ece51c0d0ecb5"},"active":true,"authorizedServices":{},"id":"Instituto_Salvatierra","isEnterprise":"true","lastModified":{"$date":"2017-09-05T07:00:55.627Z"},"productType":"cuad"}
{"_id":{"$oid":"59b0eff4620ece40622722db"},"active":true,"authorizedServices":{},"id":"VSF","isEnterprise":"true","lastModified":{"$date":"2017-09-06T07:00:56.732Z"},"productType":"cuad"}
{"_id":{"$oid":"59b8d799620ece5856147d37"},"active":true,"authorizedServices":{},"id":"AMX_Ent_1879686","isEnterprise":"true","lastModified":{"$date":"2017-09-12T07:00:03.444Z"},"productType":"cloudpbx"}
{"_id":{"$oid":"59bb7a9a620ece372b58c52d"},"active":false,"authorizedServices":{},"id":"AMX_Ent_1884059","isEnterprise":"true","lastModified":{"$date":"2017-12-07T08:00:04.001Z"},"productType":"cloudpbx"}
{"_id":{"$oid":"59cb4ca4620ece5c978e522c"},"active":false,"authorizedServices":{},"id":"AMX_Ent_1898599","isEnterprise":"true","lastModified":{"$date":"2017-09-27T07:00:04.164Z"},"productType":"cloudpbx"}
{"_id":{"$oid":"59cb4ca4620ece5c978e5237"},"active":false,"authorizedServices":{},"id":"AMX_Ent_1898621","isEnterprise":"true","lastModified":{"$date":"2017-12-08T08:00:03.616Z"},"productType":"cloudpbx"}
{"_id":{"$oid":"59cdefd6620ece35dc6b0527"},"active":false,"authorizedServices":{},"id":"DEM","isEnterprise":"true","lastModified":{"$date":"2017-10-04T07:01:13.994Z"},"productType":"cuad"}
{"_id":{"$oid":"59d48730620ece67721f1634"},"active":true,"authorizedServices":{},"id":"AMX_Ent_1905816","isEnterprise":"true","lastModified":{"$date":"2017-10-03T07:00:03.568Z"},"productType":"cloudpbx"}
{"_id":{"$oid":"59d48730620ece67721f163f"},"active":false,"authorizedServices":{},"id":"AMX_Ent_1906086","isEnterprise":"true","lastModified":{"$date":"2018-03-08T08:00:03.483Z"},"productType":"cloudpbx"}
{"_id":{"$oid":"59d48730620ece67721f164a"},"active":true,"authorizedServices":{},"id":"AMX_Ent_1906635","isEnterprise":"true","lastModified":{"$date":"2017-10-03T07:00:03.568Z"},"productType":"cloudpbx"}
{"_id":{"$oid":"59d48849620ece67721f496c"},"active":true,"authorizedServices":{},"id":"SPA","isEnterprise":"true","lastModified":{"$date":"2017-10-03T07:01:29.836Z"},"productType":"cuad"}
{"_id":{"$oid":"59d5d8a7620ece578eda3df6"},"active":false,"authorizedServices":{},"id":"AMX_Ent_1908155","isEnterprise":"true","lastModified":{"$date":"2017-11-23T08:00:03.862Z"},"productType":"cloudpbx"}
{"_id":{"$oid":"59d5d8a7620ece578eda3e01"},"active":true,"authorizedServices":{},"id":"AMX_Ent_1908412","isEnterprise":"true","lastModified":{"$date":"2017-10-04T07:00:04.175Z"},"productType":"cloudpbx"}
{"_id":{"$oid":"59d5d8a7620ece578eda3e0c"},"active":true,"authorizedServices":{},"id":"AMX_Ent_1908427","isEnterprise":"true","lastModified":{"$date":"2017-10-04T07:00:04.175Z"},"productType":"cloudpbx"}
{"_id":{"$oid":"59dc7026620ece074d59d75d"},"active":false,"authorizedServices":{},"id":"AMX_Ent_1908437","isEnterprise":"true","lastModified":{"$date":"2017-12-04T08:00:04.603Z"},"productType":"cloudpbx"}
{"_id":{"$oid":"59df1421620ece654d6af310"},"active":true,"authorizedServices":{},"id":"NAH","isEnterprise":"true","lastModified":{"$date":"2017-10-11T07:01:18.542Z"},"productType":"cuad"}
{"_id":{"$oid":"59e5aa77620ece14acaff059"},"active":true,"authorizedServices":{},"id":"AMX_Ent_1165768","isEnterprise":"true","lastModified":{"$date":"2017-10-16T07:00:04.163Z"},"productType":"cloudpbx"}
{"_id":{"$oid":"59e6fc71620ece0596e1f166"},"active":true,"authorizedServices":{},"id":"DMHS","isEnterprise":"true","lastModified":{"$date":"2017-10-17T07:01:16.885Z"},"productType":"cuad"}
{"_id":{"$oid":"59e99f23620ece626d1c7410"},"active":true,"authorizedServices":{},"id":"AMX_Ent_1924733","isEnterprise":"true","lastModified":{"$date":"2017-10-19T07:00:03.425Z"},"productType":"cloudpbx"}
{"_id":{"$oid":"59f036ac620ece10af6d28ed"},"active":true,"authorizedServices":{},"id":"AMX_Ent_1930288","isEnterprise":"true","lastModified":{"$date":"2017-10-24T07:00:04.015Z"},"productType":"cloudpbx"}
{"_id":{"$oid":"59f187fd620ece7f8b4f1372"},"active":true,"authorizedServices":{},"id":"AMX_Ent_1405165","isEnterprise":"true","lastModified":{"$date":"2017-10-25T07:00:03.595Z"},"productType":"cloudpbx"}
{"_id":{"$oid":"59f1882a620ece7f8b4f1b2c"},"active":true,"authorizedServices":{},"id":"AMX_Ent_1932130","isEnterprise":"true","lastModified":{"$date":"2017-10-25T07:00:03.595Z"},"productType":"cloudpbx"}
{"_id":{"$oid":"5a02b9bb620ece374ed2b029"},"active":true,"authorizedServices":{"attributes":[{"name":"maxTrunkGroupSimultaneousCalls","value":0}],"name":"TrunkGroup"},"id":"ConectaT","isEnterprise":"true","lastModified":{"$date":"2017-11-07T08:00:03.802Z"},"productType":"cloudpbx"}
{"_id":{"$oid":"5a040b3e620ece29298e7363"},"active":true,"authorizedServices":{},"id":"AMX_Ent_1940915","isEnterprise":"true","lastModified":{"$date":"2017-11-08T08:00:04.101Z"},"productType":"cloudpbx"}
{"_id":{"$oid":"5a040b3e620ece29298e7383"},"active":true,"authorizedServices":{},"id":"AMX_Ent_1946124","isEnterprise":"true","lastModified":{"$date":"2017-11-08T08:00:04.101Z"},"productType":"cloudpbx"}
{"_id":{"$oid":"5a040b3e620ece29298e738e"},"active":false,"authorizedServices":{},"id":"AMX_Ent_1946302","isEnterprise":"true","lastModified":{"$date":"2017-11-10T08:00:03.973Z"},"productType":"cloudpbx"}
{"_id":{"$oid":"5a040b3e620ece29298e7399"},"active":false,"authorizedServices":{},"id":"AMX_Ent_1946463","isEnterprise":"true","lastModified":{"$date":"2017-11-10T08:00:03.973Z"},"productType":"cloudpbx"}
{"_id":{"$oid":"5a06ae34620ece0c849fe593"},"active":false,"authorizedServices":{},"id":"AMX_Ent_1705500","isEnterprise":"true","lastModified":{"$date":"2018-03-02T08:00:03.308Z"},"productType":"cloudpbx"}
{"_id":{"$oid":"5a0bf439620ece4d528c017f"},"active":true,"authorizedServices":{},"id":"AMX_Ent_1935672","isEnterprise":"true","lastModified":{"$date":"2017-11-14T08:00:04.217Z"},"productType":"cloudpbx"}
{"_id":{"$oid":"5a0d45be620ece3edbf3ec6f"},"active":true,"authorizedServices":{},"id":"AMX_Ent_1952379","isEnterprise":"true","lastModified":{"$date":"2017-11-15T08:00:03.292Z"},"productType":"cloudpbx"}
{"_id":{"$oid":"5a152ebc620ece60842b39be"},"active":true,"authorizedServices":{},"id":"AMX_Ent_1956192","isEnterprise":"true","lastModified":{"$date":"2017-11-21T08:00:04.297Z"},"productType":"cloudpbx"}
{"_id":{"$oid":"5a17d1d8620ece4253363d36"},"active":true,"authorizedServices":{},"id":"AMX_Ent_1958743","isEnterprise":"true","lastModified":{"$date":"2017-11-23T08:00:03.862Z"},"productType":"cloudpbx"}
{"_id":{"$oid":"5a1fbaa6620ece625e5dd8e1"},"active":true,"authorizedServices":{},"id":"AMX_Ent_1458156","isEnterprise":"true","lastModified":{"$date":"2017-11-29T08:00:05.213Z"},"productType":"cloudpbx"}
{"_id":{"$oid":"5a1fbab7620ece625e5ddba9"},"active":true,"authorizedServices":{},"id":"AMX_Ent_1749201","isEnterprise":"true","lastModified":{"$date":"2017-12-18T08:00:03.511Z"},"productType":"cloudpbx"}
{"_id":{"$oid":"5a1fbac3620ece625e5dddd7"},"active":false,"authorizedServices":{},"id":"AMX_Ent_1961698","isEnterprise":"true","lastModified":{"$date":"2018-04-04T07:00:03.827Z"},"productType":"cloudpbx"}
{"_id":{"$oid":"5a225dc3620ece4512dd3fbd"},"active":false,"authorizedServices":{},"id":"AMX_Ent_1964541","isEnterprise":"true","lastModified":{"$date":"2017-12-04T08:00:04.603Z"},"productType":"cloudpbx"}
{"_id":{"$oid":"5a225dc3620ece4512dd3fd1"},"active":false,"authorizedServices":{},"id":"AMX_Ent_1964911","isEnterprise":"true","lastModified":{"$date":"2018-04-23T07:00:02.903Z"},"productType":"cloudpbx"}
{"_id":{"$oid":"5a225dc3620ece4512dd3fdc"},"active":true,"authorizedServices":{},"id":"AMX_Ent_1965301","isEnterprise":"true","lastModified":{"$date":"2017-12-01T08:00:03.808Z"},"productType":"cloudpbx"}
{"_id":{"$oid":"5a225f0d620ece4512dd760d"},"active":true,"authorizedServices":{},"id":"SPE","isEnterprise":"true","lastModified":{"$date":"2017-12-01T08:01:35.194Z"},"productType":"cuad"}
{"_id":{"$oid":"5a27a3d9620ece0561244f09"},"active":true,"authorizedServices":{},"id":"AMX_Ent_1966829","isEnterprise":"true","lastModified":{"$date":"2017-12-05T08:00:04.288Z"},"productType":"cloudpbx"}
{"_id":{"$oid":"5a322fbf620ece6c75bd7c36"},"active":false,"authorizedServices":{},"id":"AMX_Ent_1972144","isEnterprise":"true","lastModified":{"$date":"2018-02-28T08:00:03.722Z"},"productType":"cloudpbx"}
{"_id":{"$oid":"5a338135620ece56c8b72ad8"},"active":true,"authorizedServices":{},"id":"AMX_Ent_1737791","isEnterprise":"true","lastModified":{"$date":"2017-12-14T08:00:04.353Z"},"productType":"cloudpbx"}
{"_id":{"$oid":"5a38c73e620ece02e5d9efef"},"active":false,"authorizedServices":{},"id":"AMX_Ent_1974506","isEnterprise":"true","lastModified":{"$date":"2018-03-02T08:00:03.308Z"},"productType":"cloudpbx"}
{"_id":{"$oid":"5a3b6a5a620ece5626e3b0ac"},"active":true,"authorizedServices":{},"id":"AMX_Ent_1976386","isEnterprise":"true","lastModified":{"$date":"2017-12-20T08:00:03.389Z"},"productType":"cloudpbx"}
{"_id":{"$oid":"5a3cbbc8620ece40b2ff363c"},"active":true,"authorizedServices":{},"id":"AMX_Ent_1977607","isEnterprise":"true","lastModified":{"$date":"2017-12-21T08:00:03.603Z"},"productType":"cloudpbx"}
{"_id":{"$oid":"5a44a4e4620ece47b7a05681"},"active":true,"authorizedServices":{},"id":"AMX_Ent_1980426","isEnterprise":"true","lastModified":{"$date":"2017-12-27T08:00:08.988Z"},"productType":"cloudpbx"}
{"_id":{"$oid":"5a4747cb620ece1c48302970"},"active":true,"authorizedServices":{},"id":"AMX_Ent_1981971","isEnterprise":"true","lastModified":{"$date":"2017-12-29T08:00:04.340Z"},"productType":"cloudpbx"}
{"_id":{"$oid":"5a508244620ece7d76345410"},"active":true,"authorizedServices":{},"id":"AMX_Ent_1985273","isEnterprise":"true","lastModified":{"$date":"2018-01-05T08:00:03.755Z"},"productType":"cloudpbx"}
{"_id":{"$oid":"5a55c847620ece242be04aff"},"active":true,"authorizedServices":{},"id":"AMX_Ent_1987572","isEnterprise":"true","lastModified":{"$date":"2018-01-09T08:00:03.691Z"},"productType":"cloudpbx"}
{"_id":{"$oid":"5a586b5b620ece7bf205adb7"},"active":true,"authorizedServices":{},"id":"AMX_Ent_1989717","isEnterprise":"true","lastModified":{"$date":"2018-01-11T08:00:03.564Z"},"productType":"cloudpbx"}
{"_id":{"$oid":"5a61a5c6620ece60038b9ac2"},"active":true,"authorizedServices":{},"id":"AMX_Ent_1995114","isEnterprise":"true","lastModified":{"$date":"2018-01-18T08:00:03.948Z"},"productType":"cloudpbx"}
{"_id":{"$oid":"5a62f764620ece49e6dd8e90"},"active":true,"authorizedServices":{},"id":"AMX_Ent_1995862","isEnterprise":"true","lastModified":{"$date":"2018-01-19T08:00:04.238Z"},"productType":"cloudpbx"}
{"_id":{"$oid":"5a698eae620ece59c4d5a8ef"},"active":true,"authorizedServices":{},"id":"AMX_Ent_1999120","isEnterprise":"true","lastModified":{"$date":"2018-01-24T08:00:03.836Z"},"productType":"cloudpbx"}
{"_id":{"$oid":"5a6ae037620ece43651f7c92"},"active":true,"authorizedServices":{},"id":"AMX_Ent_2000508","isEnterprise":"true","lastModified":{"$date":"2018-01-25T08:00:03.482Z"},"productType":"cloudpbx"}
{"_id":{"$oid":"5a702606620ece69b825a586"},"active":true,"authorizedServices":{},"id":"AMX_Ent_1242849","isEnterprise":"true","lastModified":{"$date":"2018-01-29T08:00:04.016Z"},"productType":"cloudpbx"}
{"_id":{"$oid":"5a72c938620ece3c7d08646a"},"active":true,"authorizedServices":{},"id":"AMX_Ent_2003932","isEnterprise":"true","lastModified":{"$date":"2018-01-31T08:00:03.517Z"},"productType":"cloudpbx"}
{"_id":{"$oid":"5a756c30620ece0eb1fa7e92"},"active":true,"authorizedServices":{},"id":"AMX_Ent_2005114","isEnterprise":"true","lastModified":{"$date":"2018-02-02T08:00:03.708Z"},"productType":"cloudpbx"}
{"_id":{"$oid":"5a7ab237620ece317611586f"},"active":true,"authorizedServices":{},"id":"AMX_Ent_1954735","isEnterprise":"true","lastModified":{"$date":"2018-02-06T08:00:03.482Z"},"productType":"cloudpbx"}
{"_id":{"$oid":"5a7ab23b620ece3176115a12"},"active":true,"authorizedServices":{},"id":"AMX_Ent_2007591","isEnterprise":"true","lastModified":{"$date":"2018-02-06T08:00:03.482Z"},"productType":"cloudpbx"}
{"_id":{"$oid":"5a7ab2c4620ece3176116f46"},"active":true,"authorizedServices":{},"id":"Fundacion_TELMEX","isEnterprise":"true","lastModified":{"$date":"2018-02-06T08:01:20.227Z"},"productType":"cuad"}
{"_id":{"$oid":"5a7c03b8620ece1ab81afe83"},"active":false,"authorizedServices":{},"id":"AMX_Ent_2008746","isEnterprise":"true","lastModified":{"$date":"2018-02-21T08:00:03.753Z"},"productType":"cloudpbx"}
{"_id":{"$oid":"5a9661c4620ece5b4e1cdf9f"},"active":false,"authorizedServices":{},"id":"AMX_Ent_2022852","isEnterprise":"true","lastModified":{"$date":"2018-03-07T08:00:03.838Z"},"productType":"cloudpbx"}
{"_id":{"$oid":"5aa0edbd620ece2de81ad8ae"},"active":true,"authorizedServices":{},"id":"AMX_Ent_2030022","isEnterprise":"true","lastModified":{"$date":"2018-03-07T08:00:03.838Z"},"productType":"cloudpbx"}
{"_id":{"$oid":"5aa0edbd620ece2de81ad8b9"},"active":true,"authorizedServices":{},"id":"AMX_Ent_2030366","isEnterprise":"true","lastModified":{"$date":"2018-03-07T08:00:03.838Z"},"productType":"cloudpbx"}
{"_id":{"$oid":"5aa390b9620ece017ed16b2a"},"active":true,"authorizedServices":{},"id":"AMX_Ent_2020593","isEnterprise":"true","lastModified":{"$date":"2018-03-09T08:00:02.914Z"},"productType":"cloudpbx"}
{"_id":{"$oid":"5aa8d6b7620ece26c588dbd4"},"active":false,"authorizedServices":{},"id":"AMX_Ent_2034618","isEnterprise":"true","lastModified":{"$date":"2018-04-03T07:00:03.279Z"},"productType":"cloudpbx"}
{"_id":{"$oid":"5aa8d6b7620ece26c588dbdf"},"active":true,"authorizedServices":{},"id":"AMX_Ent_2035514","isEnterprise":"true","lastModified":{"$date":"2018-03-13T08:00:03.752Z"},"productType":"cloudpbx"}
{"_id":{"$oid":"5aaa2838620ece1075a5a936"},"active":true,"authorizedServices":{},"id":"AMX_Ent_2014806","isEnterprise":"true","lastModified":{"$date":"2018-03-14T08:00:03.322Z"},"productType":"cloudpbx"}
{"_id":{"$oid":"5ab362c2620ece766857c7c3"},"active":false,"authorizedServices":{},"id":"AMX_Ent_2041767","isEnterprise":"true","lastModified":{"$date":"2018-06-27T07:00:02.190Z"},"productType":"cloudpbx"}
{"_id":{"$oid":"5ab4b436620ece60402d8eb2"},"active":true,"authorizedServices":{},"id":"AMX_Ent_2042115","isEnterprise":"true","lastModified":{"$date":"2018-03-22T08:00:03.488Z"},"productType":"cloudpbx"}
{"_id":{"$oid":"5abdeeb4620ece43fe78e5fb"},"active":true,"authorizedServices":{},"id":"AMX_Ent_1849089","isEnterprise":"true","lastModified":{"$date":"2018-03-29T08:00:03.731Z"},"productType":"cloudpbx"}
{"_id":{"$oid":"5ac32677620ece6424e5f80f"},"active":true,"authorizedServices":{},"id":"AMX_Ent_1247167","isEnterprise":"true","lastModified":{"$date":"2018-04-02T07:00:03.830Z"},"productType":"cloudpbx"}
{"_id":{"$oid":"5ac71b23620ece21bf65d69e"},"active":true,"authorizedServices":{},"id":"AMX_Ent_2052974","isEnterprise":"true","lastModified":{"$date":"2018-04-05T07:00:03.040Z"},"productType":"cloudpbx"}
{"_id":{"$oid":"5acc6126620ece464da2d53e"},"active":true,"authorizedServices":{},"id":"AMX_Ent_2054084","isEnterprise":"true","lastModified":{"$date":"2018-04-09T07:00:03.448Z"},"productType":"cloudpbx"}
{"_id":{"$oid":"5acdb2a8620ece2fc4345e85"},"active":true,"authorizedServices":{},"id":"AMX_Ent_2055947","isEnterprise":"true","lastModified":{"$date":"2018-04-10T07:00:02.970Z"},"productType":"cloudpbx"}
{"_id":{"$oid":"5ad055a6620ece02973761ba"},"active":true,"authorizedServices":{},"id":"AMX_Ent_2058333","isEnterprise":"true","lastModified":{"$date":"2018-04-12T07:00:03.192Z"},"productType":"cloudpbx"}
{"_id":{"$oid":"5ad6ed2c620ece1152872bab"},"active":true,"authorizedServices":{},"id":"AMX_Ent_2049568","isEnterprise":"true","lastModified":{"$date":"2018-04-17T07:00:03.419Z"},"productType":"cloudpbx"}
{"_id":{"$oid":"5ad6ed2c620ece1152872bc4"},"active":true,"authorizedServices":{},"id":"AMX_Ent_2062570","isEnterprise":"true","lastModified":{"$date":"2018-04-17T07:00:03.419Z"},"productType":"cloudpbx"}
{"_id":{"$oid":"5ad83ea7620ece7a96f1ca6e"},"active":true,"authorizedServices":{},"id":"AMX_Ent_2063322","isEnterprise":"true","lastModified":{"$date":"2018-04-18T07:00:03.444Z"},"productType":"cloudpbx"}
{"_id":{"$oid":"5ad9902c620ece68b8a8b377"},"active":true,"authorizedServices":{},"id":"AMX_Ent_2065070","isEnterprise":"true","lastModified":{"$date":"2018-04-19T07:00:03.070Z"},"productType":"cloudpbx"}
{"_id":{"$oid":"5ae2cc4f620ece4cba3bb293"},"active":true,"authorizedServices":{},"id":"cr_solutions","isEnterprise":"true","lastModified":{"$date":"2018-04-26T07:01:30.116Z"},"productType":"cuad"}
{"_id":{"$oid":"5aec052a620ece30fe857787"},"active":true,"authorizedServices":{},"id":"AMX_Ent_2075361","isEnterprise":"true","lastModified":{"$date":"2018-05-03T07:00:03.356Z"},"productType":"cloudpbx"}
{"_id":{"$oid":"5aed56b7620ece1af42e8147"},"active":true,"authorizedServices":{},"id":"AMX_Ent_2076808","isEnterprise":"true","lastModified":{"$date":"2018-05-04T07:00:03.760Z"},"productType":"cloudpbx"}
{"_id":{"$oid":"5af29c98620ece4117e647be"},"active":true,"authorizedServices":{},"id":"AMX_Ent_1782801","isEnterprise":"true","lastModified":{"$date":"2018-05-08T07:00:03.207Z"},"productType":"cloudpbx"}
{"_id":{"$oid":"5af3ee2d620ece2b1d106f59"},"active":true,"authorizedServices":{},"id":"AMX_Ent_2080279","isEnterprise":"true","lastModified":{"$date":"2018-05-09T07:00:03.179Z"},"productType":"cloudpbx"}
{"_id":{"$oid":"5afa85ba620ece3b170772a6"},"active":true,"authorizedServices":{},"id":"AMX_Ent_2083199","isEnterprise":"true","lastModified":{"$date":"2018-05-14T07:00:03.083Z"},"productType":"cloudpbx"}
{"_id":{"$oid":"5affcbc9620ece60912fd87f"},"active":true,"authorizedServices":{},"id":"AMX_Ent_2087589","isEnterprise":"true","lastModified":{"$date":"2018-05-18T07:00:03.262Z"},"productType":"cloudpbx"}
{"_id":{"$oid":"5b0cfa8af001710b25b78a02"},"active":true,"authorizedServices":{},"id":"AMX_Ent_1503488","isEnterprise":"true","lastModified":{"$date":"2018-05-28T07:00:02.959Z"},"productType":"cloudpbx"}
{"_id":{"$oid":"5b1786a9f001717536ce7942"},"active":true,"authorizedServices":{},"id":"AMX_Ent_2101454","isEnterprise":"true","lastModified":{"$date":"2018-06-05T07:00:02.911Z"},"productType":"cloudpbx"}
{"_id":{"$oid":"5b2212a9f001716585bd3a38"},"active":true,"authorizedServices":{},"id":"AMX_Ent_2109973","isEnterprise":"true","lastModified":{"$date":"2018-06-13T07:00:02.349Z"},"productType":"cloudpbx"}
{"_id":{"$oid":"5b2212a9f001716585bd3a43"},"active":true,"authorizedServices":{},"id":"AMX_Ent_2110928","isEnterprise":"true","lastModified":{"$date":"2018-06-13T07:00:02.349Z"},"productType":"cloudpbx"}
{"_id":{"$oid":"5b24b595f0017146c50f3298"},"active":true,"authorizedServices":{},"id":"AMX_Ent_1802499","isEnterprise":"true","lastModified":{"$date":"2018-06-15T07:00:02.833Z"},"productType":"cloudpbx"}
{"_id":{"$oid":"5b29fbacf001717bb2b91c5a"},"active":true,"authorizedServices":{},"id":"AMX_Ent_2116994","isEnterprise":"true","lastModified":{"$date":"2018-06-19T07:00:02.650Z"},"productType":"cloudpbx"}
{"_id":{"$oid":"5b2b4d2cf001716ce93ae69f"},"active":true,"authorizedServices":{},"id":"AMX_Ent_2110617","isEnterprise":"true","lastModified":{"$date":"2018-06-20T07:00:03.034Z"},"productType":"cloudpbx"}
{"_id":{"$oid":"5b2b4d2df001716ce93ae6d9"},"active":true,"authorizedServices":{},"id":"AMX_Ent_2118251","isEnterprise":"true","lastModified":{"$date":"2018-06-20T07:00:03.034Z"},"productType":"cloudpbx"}
{"_id":{"$oid":"5b33362ef0017101610637d1"},"active":true,"authorizedServices":{},"id":"AMX_Ent_2123415","isEnterprise":"true","lastModified":{"$date":"2018-06-26T07:00:02.349Z"},"productType":"cloudpbx"}
{"_id":{"$oid":"5b35d931f001716669336f0e"},"active":true,"authorizedServices":{},"id":"AMX_Ent_2126862","isEnterprise":"true","lastModified":{"$date":"2018-06-28T07:00:02.965Z"},"productType":"cloudpbx"}
{"_id":{"$oid":"5b372ac7f001715bd00a155e"},"active":true,"authorizedServices":{},"id":"CECOBAM_Mexico","isEnterprise":"true","lastModified":{"$date":"2018-06-29T07:01:08.165Z"},"productType":"cuad"}
{"_id":{"$oid":"5b406532f001716127aeef43"},"active":true,"authorizedServices":{},"id":"AMX_Ent_2134867","isEnterprise":"true","lastModified":{"$date":"2018-07-06T07:00:02.887Z"},"productType":"cloudpbx"}
{"_id":{"$oid":"5b430832f001713bad14dd67"},"active":true,"authorizedServices":{},"id":"AMX_Ent_2135505","isEnterprise":"true","lastModified":{"$date":"2018-07-08T07:00:02.823Z"},"productType":"cloudpbx"}
{"_id":{"$oid":"5b4459aff001712a867107ba"},"active":true,"authorizedServices":{},"id":"AMX_Ent_2097040","isEnterprise":"true","lastModified":{"$date":"2018-07-09T07:00:02.649Z"},"productType":"cloudpbx"}
